{"assets":{"0CBCC992B49FB240DB36CA943C52B115":{"type":"texture","index":1,"assetRequest":{"type":"slide","state":"contents","slide":"none"},"url":{"native":"assets\/A357B83D-006E-4514-9516-88676D0334A4.pdf"},"width":1590,"height":1083},"15F29FF383634C416491853B012D32A9":{"type":"texture","index":8,"assetRequest":{"type":"slide","state":"contents","slide":"none"},"url":{"native":"assets\/A357B83D-006E-4514-9516-88676D0334A4.pdf"},"width":1920,"height":1080},"C4A3951E6F50F64E0D3B9F347CEB2AE1":{"type":"texture","index":6,"assetRequest":{"type":"slide","state":"contents","slide":"none"},"url":{"native":"assets\/A357B83D-006E-4514-9516-88676D0334A4.pdf"},"width":198,"height":203},"8C9F0787747E2AC327B7ABBD70025D54":{"type":"texture","index":4,"assetRequest":{"type":"slide","state":"contents","slide":"none"},"url":{"native":"assets\/A357B83D-006E-4514-9516-88676D0334A4.pdf"},"width":228,"height":235},"C25C25FF361FB24FC35F6B120D2F252D":{"type":"texture","index":0,"assetRequest":{"type":"slide","state":"contents","slide":"none"},"url":{"native":"assets\/A357B83D-006E-4514-9516-88676D0334A4.pdf"},"width":1920,"height":1080},"813CA334C8CDFC857C5488184BE80DF3":{"type":"texture","index":5,"assetRequest":{"type":"slide","state":"contents","slide":"none"},"url":{"native":"assets\/A357B83D-006E-4514-9516-88676D0334A4.pdf"},"width":177,"height":183},"90133734F572A8BA02F77D41A855A5F8":{"type":"texture","index":3,"assetRequest":{"type":"slide","state":"contents","slide":"none"},"url":{"native":"assets\/A357B83D-006E-4514-9516-88676D0334A4.pdf"},"width":132,"height":137},"83408B2AE91F6BC206FBD4B66C03D0E1":{"type":"texture","index":2,"assetRequest":{"type":"slide","state":"contents","slide":"none"},"url":{"native":"assets\/A357B83D-006E-4514-9516-88676D0334A4.pdf"},"width":237,"height":245},"FEF403319AD5AC6FABBB18660ADA8AE2":{"type":"texture","index":7,"assetRequest":{"type":"slide","state":"contents","slide":"none"},"url":{"native":"assets\/A357B83D-006E-4514-9516-88676D0334A4.pdf"},"width":1920,"height":1080}},"events":[{"effects":[{"beginTime":0,"baseLayer":{"animations":[],"initialState":{"affineTransform":[1,0,0,1,0,0],"masksToBounds":false,"rotation":0,"scale":1,"position":{"pointX":1672.7532986151359,"pointY":673.47668420808657},"width":237,"sublayerTransform":[1,0,0,0,0,1,0,0,0,0,1,0,0,0,0,1],"contentsRect":{"y":0,"x":0,"width":1,"height":1},"opacity":1,"edgeAntialiasingMask":251658240,"height":245,"hidden":false,"anchorPoint":{"pointX":0.5,"pointY":0.5}},"objectID":"F2A13A65-6739-4ECE-B5A7-FD53FE9543C8","layers":[{"animations":[],"initialState":{"affineTransform":[1,0,0,1,0,0],"masksToBounds":false,"rotation":0,"scale":1,"position":{"pointX":-594.25329861513592,"pointY":-10.976684208086567},"width":237,"sublayerTransform":[1,0,0,0,0,1,0,0,0,0,1,-0.00035007912466775983,0,0,0,1],"contentsRect":{"y":0,"x":0,"width":1,"height":1},"opacity":1,"edgeAntialiasingMask":251658240,"height":245,"hidden":false,"anchorPoint":{"pointX":-2.5073978844520504,"pointY":-0.04480279268606762}},"layers":[{"animations":[{"timeOffset":0,"from":{"scalar":true},"beginTime":1e-100,"repeatCount":0,"fillMode":"both","property":"hidden","autoreverses":false,"duration":0.01,"to":{"scalar":false}}],"layers":[],"texturedRectangle":{"singleTextureOpacity":1,"textXHeight":0,"shapePath":{"lineWidth":1,"flatness":0.59999999999999998,"lineCapStyle":0,"elements":[{"type":"MoveToPoint","points":[[197.77725933771535,40.889313213421588]]},{"type":"AddCurve","points":[[241.59101483260952,86.10615188720169],[241.59101483260952,159.41713230045571],[197.77725933771535,204.63397097423581]]},{"type":"AddCurve","points":[[153.96350384282096,249.85080964801591],[82.927370731200881,249.85080964801591],[39.113615236306714,204.63397097423581]]},{"type":"AddCurve","points":[[-4.7001402585876804,159.41713230045582],[-4.7001402585876804,86.10615188720169],[39.113615236306487,40.889313213421588]]},{"type":"AddCurve","points":[[82.927370731200881,-4.3275254603584017],[153.96350384282096,-4.3275254603585154],[197.77725933771535,40.889313213421588]]},{"type":"CloseSubpath"},{"type":"MoveToPoint","points":[[197.77725933771535,40.889313213421588]]}],"windingRule":0,"lineJoinStyle":0,"miterLimit":10},"isBackgroundTexture":true,"textBaseline":0,"isVerticalText":false,"textureType":5},"initialState":{"affineTransform":[1,0,0,1,0,0],"masksToBounds":false,"rotation":0,"scale":1,"position":{"pointX":117.24670138486408,"pointY":120.52331579191343},"width":237,"sublayerTransform":[1,0,0,0,0,1,0,0,0,0,1,0,0,0,0,1],"contentsRect":{"y":0,"x":0,"width":1,"height":1},"opacity":1,"edgeAntialiasingMask":0,"height":245,"hidden":true,"anchorPoint":{"pointX":0.5,"pointY":0.5}},"texture":"83408B2AE91F6BC206FBD4B66C03D0E1"}]}]},"effects":[],"duration":0.01,"type":"buildIn","attributes":{"direction":0},"name":"apple:appear","objectID":"F2A13A65-6739-4ECE-B5A7-FD53FE9543C8"}],"automaticPlay":false,"hyperlinks":[],"accessibility":[{"text":"IMG_0013.jpeg","targetRectangle":{"y":-8.1713048771803187e-08,"x":166.87493884811059,"width":1586.2501220703125,"height":1080.0000000000002}}],"baseLayer":{"animations":[],"initialState":{"affineTransform":[1,0,0,1,0,0],"masksToBounds":false,"rotation":0,"scale":1,"position":{"pointX":960,"pointY":540},"width":1920,"sublayerTransform":[1,0,0,0,0,1,0,0,0,0,1,0,0,0,0,1],"contentsRect":{"y":0,"x":0,"width":1,"height":1},"opacity":1,"edgeAntialiasingMask":251658240,"height":1080,"hidden":false,"anchorPoint":{"pointX":0.5,"pointY":0.5}},"layers":[{"animations":[],"initialState":{"affineTransform":[1,0,0,1,0,0],"masksToBounds":false,"rotation":0,"scale":1,"position":{"pointX":960,"pointY":540},"width":1920,"sublayerTransform":[1,0,0,0,0,1,0,0,0,0,1,0,0,0,0,1],"contentsRect":{"y":0,"x":0,"width":1,"height":1},"opacity":1,"edgeAntialiasingMask":251658240,"height":1080,"hidden":false,"anchorPoint":{"pointX":0.5,"pointY":0.5}},"layers":[{"animations":[],"initialState":{"affineTransform":[1,0,0,1,0,0],"masksToBounds":false,"rotation":0,"scale":1,"position":{"pointX":960,"pointY":540},"width":1920,"sublayerTransform":[1,0,0,0,0,1,0,0,0,0,1,0,0,0,0,1],"contentsRect":{"y":0,"x":0,"width":1,"height":1},"opacity":1,"edgeAntialiasingMask":251658240,"height":1080,"hidden":false,"anchorPoint":{"pointX":0.5,"pointY":0.5}},"layers":[{"animations":[],"layers":[],"texturedRectangle":{"isBackgroundTexture":true,"singleTextureOpacity":1,"textureType":1,"textBaseline":0,"textXHeight":0,"isVerticalText":false},"initialState":{"affineTransform":[1,0,0,1,0,0],"masksToBounds":false,"rotation":0,"scale":1,"position":{"pointX":960,"pointY":540},"width":1920,"sublayerTransform":[1,0,0,0,0,1,0,0,0,0,1,0,0,0,0,1],"contentsRect":{"y":0,"x":0,"width":1,"height":1},"opacity":1,"edgeAntialiasingMask":0,"height":1080,"hidden":false,"anchorPoint":{"pointX":0.5,"pointY":0.5}},"texture":"C25C25FF361FB24FC35F6B120D2F252D"}]}]},{"animations":[],"initialState":{"affineTransform":[1,0,0,1,0,0],"masksToBounds":false,"rotation":0,"scale":1,"position":{"pointX":960,"pointY":540},"width":1920,"sublayerTransform":[1,0,0,0,0,1,0,0,0,0,1,0,0,0,0,1],"contentsRect":{"y":0,"x":0,"width":1,"height":1},"opacity":1,"edgeAntialiasingMask":251658240,"height":1080,"hidden":false,"anchorPoint":{"pointX":0.5,"pointY":0.5}},"layers":[{"animations":[],"initialState":{"affineTransform":[1,0,0,1,0,0],"masksToBounds":false,"rotation":0,"scale":1,"position":{"pointX":961.87493884811056,"pointY":541.4999999182869},"width":1590,"sublayerTransform":[1,0,0,0,0,1,0,0,0,0,1,0,0,0,0,1],"contentsRect":{"y":0,"x":0,"width":1,"height":1},"opacity":1,"edgeAntialiasingMask":251658240,"height":1083,"hidden":false,"anchorPoint":{"pointX":0.5,"pointY":0.5}},"layers":[{"animations":[],"layers":[],"texturedRectangle":{"isBackgroundTexture":true,"singleTextureOpacity":1,"textureType":5,"textBaseline":0,"textXHeight":0,"isVerticalText":false},"initialState":{"affineTransform":[1,0,0,1,0,0],"masksToBounds":false,"rotation":0,"scale":1,"position":{"pointX":793.12506115188944,"pointY":539.5000000817131},"width":1590,"sublayerTransform":[1,0,0,0,0,1,0,0,0,0,1,0,0,0,0,1],"contentsRect":{"y":0,"x":0,"width":1,"height":1},"opacity":1,"edgeAntialiasingMask":0,"height":1083,"hidden":false,"anchorPoint":{"pointX":0.5,"pointY":0.5}},"texture":"0CBCC992B49FB240DB36CA943C52B115"}]}]},{"animations":[],"initialState":{"affineTransform":[1,0,0,1,0,0],"masksToBounds":false,"rotation":0,"scale":1,"position":{"pointX":960,"pointY":540},"width":1920,"sublayerTransform":[1,0,0,0,0,1,0,0,0,0,1,0,0,0,0,1],"contentsRect":{"y":0,"x":0,"width":1,"height":1},"opacity":1,"edgeAntialiasingMask":251658240,"height":1080,"hidden":false,"anchorPoint":{"pointX":0.5,"pointY":0.5}},"layers":[{"animations":[],"initialState":{"affineTransform":[1,0,0,1,0,0],"masksToBounds":false,"rotation":0,"scale":1,"position":{"pointX":1672.7532986151359,"pointY":673.47668420808657},"width":237,"sublayerTransform":[1,0,0,0,0,1,0,0,0,0,1,0,0,0,0,1],"contentsRect":{"y":0,"x":0,"width":1,"height":1},"opacity":1,"edgeAntialiasingMask":251658240,"height":245,"hidden":false,"anchorPoint":{"pointX":0.5,"pointY":0.5}},"objectID":"F2A13A65-6739-4ECE-B5A7-FD53FE9543C8","layers":[{"animations":[],"layers":[],"texturedRectangle":{"singleTextureOpacity":1,"textXHeight":0,"shapePath":{"lineWidth":1,"flatness":0.59999999999999998,"lineCapStyle":0,"elements":[{"type":"MoveToPoint","points":[[197.77725933771535,40.889313213421588]]},{"type":"AddCurve","points":[[241.59101483260952,86.10615188720169],[241.59101483260952,159.41713230045571],[197.77725933771535,204.63397097423581]]},{"type":"AddCurve","points":[[153.96350384282096,249.85080964801591],[82.927370731200881,249.85080964801591],[39.113615236306714,204.63397097423581]]},{"type":"AddCurve","points":[[-4.7001402585876804,159.41713230045582],[-4.7001402585876804,86.10615188720169],[39.113615236306487,40.889313213421588]]},{"type":"AddCurve","points":[[82.927370731200881,-4.3275254603584017],[153.96350384282096,-4.3275254603585154],[197.77725933771535,40.889313213421588]]},{"type":"CloseSubpath"},{"type":"MoveToPoint","points":[[197.77725933771535,40.889313213421588]]}],"windingRule":0,"lineJoinStyle":0,"miterLimit":10},"isBackgroundTexture":true,"textBaseline":0,"isVerticalText":false,"textureType":5},"initialState":{"affineTransform":[1,0,0,1,0,0],"masksToBounds":false,"rotation":0,"scale":1,"position":{"pointX":117.24670138486408,"pointY":120.52331579191343},"width":237,"sublayerTransform":[1,0,0,0,0,1,0,0,0,0,1,0,0,0,0,1],"contentsRect":{"y":0,"x":0,"width":1,"height":1},"opacity":1,"edgeAntialiasingMask":0,"height":245,"hidden":true,"anchorPoint":{"pointX":0.5,"pointY":0.5}},"texture":"83408B2AE91F6BC206FBD4B66C03D0E1"}]}]},{"animations":[],"initialState":{"affineTransform":[1,0,0,1,0,0],"masksToBounds":false,"rotation":0,"scale":1,"position":{"pointX":960,"pointY":540},"width":1920,"sublayerTransform":[1,0,0,0,0,1,0,0,0,0,1,0,0,0,0,1],"contentsRect":{"y":0,"x":0,"width":1,"height":1},"opacity":1,"edgeAntialiasingMask":251658240,"height":1080,"hidden":false,"anchorPoint":{"pointX":0.5,"pointY":0.5}},"layers":[{"animations":[],"initialState":{"affineTransform":[1,0,0,1,0,0],"masksToBounds":false,"rotation":0,"scale":1,"position":{"pointX":1400.090933499562,"pointY":391.45167809516045},"width":132,"sublayerTransform":[1,0,0,0,0,1,0,0,0,0,1,0,0,0,0,1],"contentsRect":{"y":0,"x":0,"width":1,"height":1},"opacity":1,"edgeAntialiasingMask":251658240,"height":137,"hidden":false,"anchorPoint":{"pointX":0.5,"pointY":0.5}},"objectID":"462E5D91-BC20-40AC-BB85-94174BDBC93B","layers":[{"animations":[],"layers":[],"texturedRectangle":{"singleTextureOpacity":1,"textXHeight":0,"shapePath":{"lineWidth":1,"flatness":0.59999999999999998,"lineCapStyle":0,"elements":[{"type":"MoveToPoint","points":[[108.219011892342,25.035222479737172]]},{"type":"AddCurve","points":[[131.58222905713978,49.146617535188966],[131.58222905713978,88.238906056140081],[108.219011892342,112.35030111159188]]},{"type":"AddCurve","points":[[84.855802864128464,136.46169616704367],[46.976553240093608,136.46169616704367],[23.613342177734012,112.35030111159188]]},{"type":"AddCurve","points":[[0.25013060683795629,88.238906056140081],[0.25013060683795629,49.146617535188966],[23.613342177734012,25.035222479737172]]},{"type":"AddCurve","points":[[46.976553240093608,0.92382996696824193],[84.855802864128464,0.92382996696824193],[108.219011892342,25.035222479737172]]},{"type":"CloseSubpath"},{"type":"MoveToPoint","points":[[108.219011892342,25.035222479737172]]}],"windingRule":0,"lineJoinStyle":0,"miterLimit":10},"isBackgroundTexture":true,"textBaseline":0,"isVerticalText":false,"textureType":5},"initialState":{"affineTransform":[1,0,0,1,0,0],"masksToBounds":false,"rotation":0,"scale":1,"position":{"pointX":64.90906650043803,"pointY":66.548321904839554},"width":132,"sublayerTransform":[1,0,0,0,0,1,0,0,0,0,1,0,0,0,0,1],"contentsRect":{"y":0,"x":0,"width":1,"height":1},"opacity":1,"edgeAntialiasingMask":0,"height":137,"hidden":true,"anchorPoint":{"pointX":0.5,"pointY":0.5}},"texture":"90133734F572A8BA02F77D41A855A5F8"}]}]},{"animations":[],"initialState":{"affineTransform":[1,0,0,1,0,0],"masksToBounds":false,"rotation":0,"scale":1,"position":{"pointX":960,"pointY":540},"width":1920,"sublayerTransform":[1,0,0,0,0,1,0,0,0,0,1,0,0,0,0,1],"contentsRect":{"y":0,"x":0,"width":1,"height":1},"opacity":1,"edgeAntialiasingMask":251658240,"height":1080,"hidden":false,"anchorPoint":{"pointX":0.5,"pointY":0.5}},"layers":[{"animations":[],"initialState":{"affineTransform":[1,0,0,1,0,0],"masksToBounds":false,"rotation":0,"scale":1,"position":{"pointX":945.21406487519459,"pointY":964.83098255654579},"width":228,"sublayerTransform":[1,0,0,0,0,1,0,0,0,0,1,0,0,0,0,1],"contentsRect":{"y":0,"x":0,"width":1,"height":1},"opacity":1,"edgeAntialiasingMask":251658240,"height":235,"hidden":false,"anchorPoint":{"pointX":0.5,"pointY":0.5}},"objectID":"12A2E71C-DA99-46E0-943B-1E52D1E332BA","layers":[{"animations":[],"layers":[],"texturedRectangle":{"singleTextureOpacity":1,"textXHeight":0,"shapePath":{"lineWidth":1,"flatness":0.59999999999999998,"lineCapStyle":0,"elements":[{"type":"MoveToPoint","points":[[190.17563330299322,38.904559463333726]]},{"type":"AddCurve","points":[[232.25939852009446,82.335999919141841],[232.25939852009446,152.75226564222635],[190.17563330299322,196.18370609803446]]},{"type":"AddCurve","points":[[148.09188274218263,239.61514655384258],[79.860635455753936,239.61514655384258],[37.776881230870686,196.18370609803446]]},{"type":"AddCurve","points":[[-4.3068739100307312,152.75226564222635],[-4.3068739100307312,82.335999919141841],[37.776881230870686,38.904559463333726]]},{"type":"AddCurve","points":[[79.860635455753936,-4.5268764123835581],[148.09188274218263,-4.5268764123835581],[190.17563330299322,38.904559463333726]]},{"type":"CloseSubpath"},{"type":"MoveToPoint","points":[[190.17563330299322,38.904559463333726]]}],"windingRule":0,"lineJoinStyle":0,"miterLimit":10},"isBackgroundTexture":true,"textBaseline":0,"isVerticalText":false,"textureType":5},"initialState":{"affineTransform":[1,0,0,1,0,0],"masksToBounds":false,"rotation":0,"scale":1,"position":{"pointX":112.78593512480541,"pointY":116.16901744345421},"width":228,"sublayerTransform":[1,0,0,0,0,1,0,0,0,0,1,0,0,0,0,1],"contentsRect":{"y":0,"x":0,"width":1,"height":1},"opacity":1,"edgeAntialiasingMask":0,"height":235,"hidden":true,"anchorPoint":{"pointX":0.5,"pointY":0.5}},"texture":"8C9F0787747E2AC327B7ABBD70025D54"}]}]},{"animations":[],"initialState":{"affineTransform":[1,0,0,1,0,0],"masksToBounds":false,"rotation":0,"scale":1,"position":{"pointX":960,"pointY":540},"width":1920,"sublayerTransform":[1,0,0,0,0,1,0,0,0,0,1,0,0,0,0,1],"contentsRect":{"y":0,"x":0,"width":1,"height":1},"opacity":1,"edgeAntialiasingMask":251658240,"height":1080,"hidden":false,"anchorPoint":{"pointX":0.5,"pointY":0.5}},"layers":[{"animations":[],"initialState":{"affineTransform":[1,0,0,1,0,0],"masksToBounds":false,"rotation":0,"scale":1,"position":{"pointX":1197.1547338490925,"pointY":362.25339465725926},"width":177,"sublayerTransform":[1,0,0,0,0,1,0,0,0,0,1,0,0,0,0,1],"contentsRect":{"y":0,"x":0,"width":1,"height":1},"opacity":1,"edgeAntialiasingMask":251658240,"height":183,"hidden":false,"anchorPoint":{"pointX":0.5,"pointY":0.5}},"objectID":"15E40DE8-D105-4B85-B7C0-A3E1087DF4E2","layers":[{"animations":[],"layers":[],"texturedRectangle":{"singleTextureOpacity":1,"textXHeight":0,"shapePath":{"lineWidth":1,"flatness":0.59999999999999998,"lineCapStyle":0,"elements":[{"type":"MoveToPoint","points":[[146.65323312499822,31.542549924699983]]},{"type":"AddCurve","points":[[178.67983533667757,64.594760433496617],[178.67983533667757,118.18297241764469],[146.65323312499822,151.23518292644133]]},{"type":"AddCurve","points":[[114.62664206705449,184.28739343523796],[62.701273603084701,184.28739343523796],[30.674679756707064,151.23518292644133]]},{"type":"AddCurve","points":[[-1.3519147867789343,118.18297241764469],[-1.3519147867789343,64.594760433496617],[30.674679756707064,31.542549924699983]]},{"type":"AddCurve","points":[[62.701273603084701,-1.5096570985542712],[114.62664206705449,-1.5096570985542712],[146.65323312499822,31.542549924699983]]},{"type":"CloseSubpath"},{"type":"MoveToPoint","points":[[146.65323312499822,31.542549924699983]]}],"windingRule":0,"lineJoinStyle":0,"miterLimit":10},"isBackgroundTexture":true,"textBaseline":0,"isVerticalText":false,"textureType":5},"initialState":{"affineTransform":[1,0,0,1,0,0],"masksToBounds":false,"rotation":0,"scale":1,"position":{"pointX":86.845266150907491,"pointY":89.746605342740736},"width":177,"sublayerTransform":[1,0,0,0,0,1,0,0,0,0,1,0,0,0,0,1],"contentsRect":{"y":0,"x":0,"width":1,"height":1},"opacity":1,"edgeAntialiasingMask":0,"height":183,"hidden":true,"anchorPoint":{"pointX":0.5,"pointY":0.5}},"texture":"813CA334C8CDFC857C5488184BE80DF3"}]}]},{"animations":[],"initialState":{"affineTransform":[1,0,0,1,0,0],"masksToBounds":false,"rotation":0,"scale":1,"position":{"pointX":960,"pointY":540},"width":1920,"sublayerTransform":[1,0,0,0,0,1,0,0,0,0,1,0,0,0,0,1],"contentsRect":{"y":0,"x":0,"width":1,"height":1},"opacity":1,"edgeAntialiasingMask":251658240,"height":1080,"hidden":false,"anchorPoint":{"pointX":0.5,"pointY":0.5}},"layers":[{"animations":[],"initialState":{"affineTransform":[1,0,0,1,0,0],"masksToBounds":false,"rotation":0,"scale":1,"position":{"pointX":1515.6884846369328,"pointY":940.81912076009428},"width":198,"sublayerTransform":[1,0,0,0,0,1,0,0,0,0,1,0,0,0,0,1],"contentsRect":{"y":0,"x":0,"width":1,"height":1},"opacity":1,"edgeAntialiasingMask":251658240,"height":203,"hidden":false,"anchorPoint":{"pointX":0.5,"pointY":0.5}},"objectID":"91D4C10C-B13B-4F1A-A313-630B732A3675","layers":[{"animations":[],"layers":[],"texturedRectangle":{"singleTextureOpacity":1,"textXHeight":0,"shapePath":{"lineWidth":1,"flatness":0.59999999999999998,"lineCapStyle":0,"elements":[{"type":"MoveToPoint","points":[[164.14461810058515,34.199452052424817]]},{"type":"AddCurve","points":[[200.1648967343674,71.373231029050544],[200.1648967343674,131.64382465609719],[164.14461810058515,168.81760363272292]]},{"type":"AddCurve","points":[[128.1243520113951,205.99138260934865],[69.723956369302186,205.99138260934865],[33.703687143964089,168.81760363272292]]},{"type":"AddCurve","points":[[-2.3165828654109646,131.64382465609719],[-2.3165828654109646,71.373231029050544],[33.703687143964089,34.199452052424817]]},{"type":"AddCurve","points":[[69.723956369302186,-2.9743230040159006],[128.1243520113951,-2.9743230040159006],[164.14461810058515,34.199452052424817]]},{"type":"CloseSubpath"},{"type":"MoveToPoint","points":[[164.14461810058515,34.199452052424817]]}],"windingRule":0,"lineJoinStyle":0,"miterLimit":10},"isBackgroundTexture":true,"textBaseline":0,"isVerticalText":false,"textureType":5},"initialState":{"affineTransform":[1,0,0,1,0,0],"masksToBounds":false,"rotation":0,"scale":1,"position":{"pointX":97.311515363067201,"pointY":100.18087923990572},"width":198,"sublayerTransform":[1,0,0,0,0,1,0,0,0,0,1,0,0,0,0,1],"contentsRect":{"y":0,"x":0,"width":1,"height":1},"opacity":1,"edgeAntialiasingMask":0,"height":203,"hidden":true,"anchorPoint":{"pointX":0.5,"pointY":0.5}},"texture":"C4A3951E6F50F64E0D3B9F347CEB2AE1"}]}]}]}},{"effects":[{"beginTime":0,"baseLayer":{"animations":[],"initialState":{"affineTransform":[1,0,0,1,0,0],"masksToBounds":false,"rotation":0,"scale":1,"position":{"pointX":1197.1547338490925,"pointY":362.25339465725926},"width":177,"sublayerTransform":[1,0,0,0,0,1,0,0,0,0,1,0,0,0,0,1],"contentsRect":{"y":0,"x":0,"width":1,"height":1},"opacity":1,"edgeAntialiasingMask":251658240,"height":183,"hidden":false,"anchorPoint":{"pointX":0.5,"pointY":0.5}},"objectID":"15E40DE8-D105-4B85-B7C0-A3E1087DF4E2","layers":[{"animations":[],"initialState":{"affineTransform":[1,0,0,1,0,0],"masksToBounds":false,"rotation":0,"scale":1,"position":{"pointX":-148.65473384909251,"pointY":269.24660534274074},"width":177,"sublayerTransform":[1,0,0,0,0,1,0,0,0,0,1,-0.00035007912466775983,0,0,0,1],"contentsRect":{"y":0,"x":0,"width":1,"height":1},"opacity":1,"edgeAntialiasingMask":251658240,"height":183,"hidden":false,"anchorPoint":{"pointX":-0.83985725338470341,"pointY":1.4712929253701679}},"layers":[{"animations":[{"timeOffset":0,"from":{"scalar":true},"beginTime":1e-100,"repeatCount":0,"fillMode":"both","property":"hidden","autoreverses":false,"duration":0.01,"to":{"scalar":false}}],"layers":[],"texturedRectangle":{"singleTextureOpacity":1,"textXHeight":0,"shapePath":{"lineWidth":1,"flatness":0.59999999999999998,"lineCapStyle":0,"elements":[{"type":"MoveToPoint","points":[[146.65323312499822,31.542549924699983]]},{"type":"AddCurve","points":[[178.67983533667757,64.594760433496617],[178.67983533667757,118.18297241764469],[146.65323312499822,151.23518292644133]]},{"type":"AddCurve","points":[[114.62664206705449,184.28739343523796],[62.701273603084701,184.28739343523796],[30.674679756707064,151.23518292644133]]},{"type":"AddCurve","points":[[-1.3519147867789343,118.18297241764469],[-1.3519147867789343,64.594760433496617],[30.674679756707064,31.542549924699983]]},{"type":"AddCurve","points":[[62.701273603084701,-1.5096570985542712],[114.62664206705449,-1.5096570985542712],[146.65323312499822,31.542549924699983]]},{"type":"CloseSubpath"},{"type":"MoveToPoint","points":[[146.65323312499822,31.542549924699983]]}],"windingRule":0,"lineJoinStyle":0,"miterLimit":10},"isBackgroundTexture":true,"textBaseline":0,"isVerticalText":false,"textureType":5},"initialState":{"affineTransform":[1,0,0,1,0,0],"masksToBounds":false,"rotation":0,"scale":1,"position":{"pointX":86.845266150907491,"pointY":89.746605342740736},"width":177,"sublayerTransform":[1,0,0,0,0,1,0,0,0,0,1,0,0,0,0,1],"contentsRect":{"y":0,"x":0,"width":1,"height":1},"opacity":1,"edgeAntialiasingMask":0,"height":183,"hidden":true,"anchorPoint":{"pointX":0.5,"pointY":0.5}},"texture":"813CA334C8CDFC857C5488184BE80DF3"}]}]},"effects":[],"duration":0.01,"type":"buildIn","attributes":{"direction":0},"name":"apple:appear","objectID":"15E40DE8-D105-4B85-B7C0-A3E1087DF4E2"}],"automaticPlay":false,"hyperlinks":[],"accessibility":[{"text":"IMG_0013.jpeg","targetRectangle":{"y":-8.1713048771803187e-08,"x":166.87493884811059,"width":1586.2501220703125,"height":1080.0000000000002}}],"baseLayer":{"animations":[],"initialState":{"affineTransform":[1,0,0,1,0,0],"masksToBounds":false,"rotation":0,"scale":1,"position":{"pointX":960,"pointY":540},"width":1920,"sublayerTransform":[1,0,0,0,0,1,0,0,0,0,1,0,0,0,0,1],"contentsRect":{"y":0,"x":0,"width":1,"height":1},"opacity":1,"edgeAntialiasingMask":251658240,"height":1080,"hidden":false,"anchorPoint":{"pointX":0.5,"pointY":0.5}},"layers":[{"animations":[],"initialState":{"affineTransform":[1,0,0,1,0,0],"masksToBounds":false,"rotation":0,"scale":1,"position":{"pointX":960,"pointY":540},"width":1920,"sublayerTransform":[1,0,0,0,0,1,0,0,0,0,1,0,0,0,0,1],"contentsRect":{"y":0,"x":0,"width":1,"height":1},"opacity":1,"edgeAntialiasingMask":251658240,"height":1080,"hidden":false,"anchorPoint":{"pointX":0.5,"pointY":0.5}},"layers":[{"animations":[],"initialState":{"affineTransform":[1,0,0,1,0,0],"masksToBounds":false,"rotation":0,"scale":1,"position":{"pointX":960,"pointY":540},"width":1920,"sublayerTransform":[1,0,0,0,0,1,0,0,0,0,1,0,0,0,0,1],"contentsRect":{"y":0,"x":0,"width":1,"height":1},"opacity":1,"edgeAntialiasingMask":251658240,"height":1080,"hidden":false,"anchorPoint":{"pointX":0.5,"pointY":0.5}},"layers":[{"animations":[],"layers":[],"texturedRectangle":{"isBackgroundTexture":true,"singleTextureOpacity":1,"textureType":1,"textBaseline":0,"textXHeight":0,"isVerticalText":false},"initialState":{"affineTransform":[1,0,0,1,0,0],"masksToBounds":false,"rotation":0,"scale":1,"position":{"pointX":960,"pointY":540},"width":1920,"sublayerTransform":[1,0,0,0,0,1,0,0,0,0,1,0,0,0,0,1],"contentsRect":{"y":0,"x":0,"width":1,"height":1},"opacity":1,"edgeAntialiasingMask":0,"height":1080,"hidden":false,"anchorPoint":{"pointX":0.5,"pointY":0.5}},"texture":"C25C25FF361FB24FC35F6B120D2F252D"}]}]},{"animations":[],"initialState":{"affineTransform":[1,0,0,1,0,0],"masksToBounds":false,"rotation":0,"scale":1,"position":{"pointX":960,"pointY":540},"width":1920,"sublayerTransform":[1,0,0,0,0,1,0,0,0,0,1,0,0,0,0,1],"contentsRect":{"y":0,"x":0,"width":1,"height":1},"opacity":1,"edgeAntialiasingMask":251658240,"height":1080,"hidden":false,"anchorPoint":{"pointX":0.5,"pointY":0.5}},"layers":[{"animations":[],"initialState":{"affineTransform":[1,0,0,1,0,0],"masksToBounds":false,"rotation":0,"scale":1,"position":{"pointX":961.87493884811056,"pointY":541.4999999182869},"width":1590,"sublayerTransform":[1,0,0,0,0,1,0,0,0,0,1,0,0,0,0,1],"contentsRect":{"y":0,"x":0,"width":1,"height":1},"opacity":1,"edgeAntialiasingMask":251658240,"height":1083,"hidden":false,"anchorPoint":{"pointX":0.5,"pointY":0.5}},"layers":[{"animations":[],"layers":[],"texturedRectangle":{"isBackgroundTexture":true,"singleTextureOpacity":1,"textureType":5,"textBaseline":0,"textXHeight":0,"isVerticalText":false},"initialState":{"affineTransform":[1,0,0,1,0,0],"masksToBounds":false,"rotation":0,"scale":1,"position":{"pointX":793.12506115188944,"pointY":539.5000000817131},"width":1590,"sublayerTransform":[1,0,0,0,0,1,0,0,0,0,1,0,0,0,0,1],"contentsRect":{"y":0,"x":0,"width":1,"height":1},"opacity":1,"edgeAntialiasingMask":0,"height":1083,"hidden":false,"anchorPoint":{"pointX":0.5,"pointY":0.5}},"texture":"0CBCC992B49FB240DB36CA943C52B115"}]}]},{"animations":[],"initialState":{"affineTransform":[1,0,0,1,0,0],"masksToBounds":false,"rotation":0,"scale":1,"position":{"pointX":960,"pointY":540},"width":1920,"sublayerTransform":[1,0,0,0,0,1,0,0,0,0,1,0,0,0,0,1],"contentsRect":{"y":0,"x":0,"width":1,"height":1},"opacity":1,"edgeAntialiasingMask":251658240,"height":1080,"hidden":false,"anchorPoint":{"pointX":0.5,"pointY":0.5}},"layers":[{"animations":[],"initialState":{"affineTransform":[1,0,0,1,0,0],"masksToBounds":false,"rotation":0,"scale":1,"position":{"pointX":1672.7532986151359,"pointY":673.47668420808657},"width":237,"sublayerTransform":[1,0,0,0,0,1,0,0,0,0,1,0,0,0,0,1],"contentsRect":{"y":0,"x":0,"width":1,"height":1},"opacity":1,"edgeAntialiasingMask":251658240,"height":245,"hidden":false,"anchorPoint":{"pointX":0.5,"pointY":0.5}},"objectID":"F2A13A65-6739-4ECE-B5A7-FD53FE9543C8","layers":[{"animations":[],"layers":[],"texturedRectangle":{"singleTextureOpacity":1,"textXHeight":0,"shapePath":{"lineWidth":1,"flatness":0.59999999999999998,"lineCapStyle":0,"elements":[{"type":"MoveToPoint","points":[[197.77725933771535,40.889313213421588]]},{"type":"AddCurve","points":[[241.59101483260952,86.10615188720169],[241.59101483260952,159.41713230045571],[197.77725933771535,204.63397097423581]]},{"type":"AddCurve","points":[[153.96350384282096,249.85080964801591],[82.927370731200881,249.85080964801591],[39.113615236306714,204.63397097423581]]},{"type":"AddCurve","points":[[-4.7001402585876804,159.41713230045582],[-4.7001402585876804,86.10615188720169],[39.113615236306487,40.889313213421588]]},{"type":"AddCurve","points":[[82.927370731200881,-4.3275254603584017],[153.96350384282096,-4.3275254603585154],[197.77725933771535,40.889313213421588]]},{"type":"CloseSubpath"},{"type":"MoveToPoint","points":[[197.77725933771535,40.889313213421588]]}],"windingRule":0,"lineJoinStyle":0,"miterLimit":10},"isBackgroundTexture":true,"textBaseline":0,"isVerticalText":false,"textureType":5},"initialState":{"affineTransform":[1,0,0,1,0,0],"masksToBounds":false,"rotation":0,"scale":1,"position":{"pointX":117.24670138486408,"pointY":120.52331579191343},"width":237,"sublayerTransform":[1,0,0,0,0,1,0,0,0,0,1,0,0,0,0,1],"contentsRect":{"y":0,"x":0,"width":1,"height":1},"opacity":1,"edgeAntialiasingMask":0,"height":245,"hidden":false,"anchorPoint":{"pointX":0.5,"pointY":0.5}},"texture":"83408B2AE91F6BC206FBD4B66C03D0E1"}]}]},{"animations":[],"initialState":{"affineTransform":[1,0,0,1,0,0],"masksToBounds":false,"rotation":0,"scale":1,"position":{"pointX":960,"pointY":540},"width":1920,"sublayerTransform":[1,0,0,0,0,1,0,0,0,0,1,0,0,0,0,1],"contentsRect":{"y":0,"x":0,"width":1,"height":1},"opacity":1,"edgeAntialiasingMask":251658240,"height":1080,"hidden":false,"anchorPoint":{"pointX":0.5,"pointY":0.5}},"layers":[{"animations":[],"initialState":{"affineTransform":[1,0,0,1,0,0],"masksToBounds":false,"rotation":0,"scale":1,"position":{"pointX":1400.090933499562,"pointY":391.45167809516045},"width":132,"sublayerTransform":[1,0,0,0,0,1,0,0,0,0,1,0,0,0,0,1],"contentsRect":{"y":0,"x":0,"width":1,"height":1},"opacity":1,"edgeAntialiasingMask":251658240,"height":137,"hidden":false,"anchorPoint":{"pointX":0.5,"pointY":0.5}},"objectID":"462E5D91-BC20-40AC-BB85-94174BDBC93B","layers":[{"animations":[],"layers":[],"texturedRectangle":{"singleTextureOpacity":1,"textXHeight":0,"shapePath":{"lineWidth":1,"flatness":0.59999999999999998,"lineCapStyle":0,"elements":[{"type":"MoveToPoint","points":[[108.219011892342,25.035222479737172]]},{"type":"AddCurve","points":[[131.58222905713978,49.146617535188966],[131.58222905713978,88.238906056140081],[108.219011892342,112.35030111159188]]},{"type":"AddCurve","points":[[84.855802864128464,136.46169616704367],[46.976553240093608,136.46169616704367],[23.613342177734012,112.35030111159188]]},{"type":"AddCurve","points":[[0.25013060683795629,88.238906056140081],[0.25013060683795629,49.146617535188966],[23.613342177734012,25.035222479737172]]},{"type":"AddCurve","points":[[46.976553240093608,0.92382996696824193],[84.855802864128464,0.92382996696824193],[108.219011892342,25.035222479737172]]},{"type":"CloseSubpath"},{"type":"MoveToPoint","points":[[108.219011892342,25.035222479737172]]}],"windingRule":0,"lineJoinStyle":0,"miterLimit":10},"isBackgroundTexture":true,"textBaseline":0,"isVerticalText":false,"textureType":5},"initialState":{"affineTransform":[1,0,0,1,0,0],"masksToBounds":false,"rotation":0,"scale":1,"position":{"pointX":64.90906650043803,"pointY":66.548321904839554},"width":132,"sublayerTransform":[1,0,0,0,0,1,0,0,0,0,1,0,0,0,0,1],"contentsRect":{"y":0,"x":0,"width":1,"height":1},"opacity":1,"edgeAntialiasingMask":0,"height":137,"hidden":true,"anchorPoint":{"pointX":0.5,"pointY":0.5}},"texture":"90133734F572A8BA02F77D41A855A5F8"}]}]},{"animations":[],"initialState":{"affineTransform":[1,0,0,1,0,0],"masksToBounds":false,"rotation":0,"scale":1,"position":{"pointX":960,"pointY":540},"width":1920,"sublayerTransform":[1,0,0,0,0,1,0,0,0,0,1,0,0,0,0,1],"contentsRect":{"y":0,"x":0,"width":1,"height":1},"opacity":1,"edgeAntialiasingMask":251658240,"height":1080,"hidden":false,"anchorPoint":{"pointX":0.5,"pointY":0.5}},"layers":[{"animations":[],"initialState":{"affineTransform":[1,0,0,1,0,0],"masksToBounds":false,"rotation":0,"scale":1,"position":{"pointX":945.21406487519459,"pointY":964.83098255654579},"width":228,"sublayerTransform":[1,0,0,0,0,1,0,0,0,0,1,0,0,0,0,1],"contentsRect":{"y":0,"x":0,"width":1,"height":1},"opacity":1,"edgeAntialiasingMask":251658240,"height":235,"hidden":false,"anchorPoint":{"pointX":0.5,"pointY":0.5}},"objectID":"12A2E71C-DA99-46E0-943B-1E52D1E332BA","layers":[{"animations":[],"layers":[],"texturedRectangle":{"singleTextureOpacity":1,"textXHeight":0,"shapePath":{"lineWidth":1,"flatness":0.59999999999999998,"lineCapStyle":0,"elements":[{"type":"MoveToPoint","points":[[190.17563330299322,38.904559463333726]]},{"type":"AddCurve","points":[[232.25939852009446,82.335999919141841],[232.25939852009446,152.75226564222635],[190.17563330299322,196.18370609803446]]},{"type":"AddCurve","points":[[148.09188274218263,239.61514655384258],[79.860635455753936,239.61514655384258],[37.776881230870686,196.18370609803446]]},{"type":"AddCurve","points":[[-4.3068739100307312,152.75226564222635],[-4.3068739100307312,82.335999919141841],[37.776881230870686,38.904559463333726]]},{"type":"AddCurve","points":[[79.860635455753936,-4.5268764123835581],[148.09188274218263,-4.5268764123835581],[190.17563330299322,38.904559463333726]]},{"type":"CloseSubpath"},{"type":"MoveToPoint","points":[[190.17563330299322,38.904559463333726]]}],"windingRule":0,"lineJoinStyle":0,"miterLimit":10},"isBackgroundTexture":true,"textBaseline":0,"isVerticalText":false,"textureType":5},"initialState":{"affineTransform":[1,0,0,1,0,0],"masksToBounds":false,"rotation":0,"scale":1,"position":{"pointX":112.78593512480541,"pointY":116.16901744345421},"width":228,"sublayerTransform":[1,0,0,0,0,1,0,0,0,0,1,0,0,0,0,1],"contentsRect":{"y":0,"x":0,"width":1,"height":1},"opacity":1,"edgeAntialiasingMask":0,"height":235,"hidden":true,"anchorPoint":{"pointX":0.5,"pointY":0.5}},"texture":"8C9F0787747E2AC327B7ABBD70025D54"}]}]},{"animations":[],"initialState":{"affineTransform":[1,0,0,1,0,0],"masksToBounds":false,"rotation":0,"scale":1,"position":{"pointX":960,"pointY":540},"width":1920,"sublayerTransform":[1,0,0,0,0,1,0,0,0,0,1,0,0,0,0,1],"contentsRect":{"y":0,"x":0,"width":1,"height":1},"opacity":1,"edgeAntialiasingMask":251658240,"height":1080,"hidden":false,"anchorPoint":{"pointX":0.5,"pointY":0.5}},"layers":[{"animations":[],"initialState":{"affineTransform":[1,0,0,1,0,0],"masksToBounds":false,"rotation":0,"scale":1,"position":{"pointX":1197.1547338490925,"pointY":362.25339465725926},"width":177,"sublayerTransform":[1,0,0,0,0,1,0,0,0,0,1,0,0,0,0,1],"contentsRect":{"y":0,"x":0,"width":1,"height":1},"opacity":1,"edgeAntialiasingMask":251658240,"height":183,"hidden":false,"anchorPoint":{"pointX":0.5,"pointY":0.5}},"objectID":"15E40DE8-D105-4B85-B7C0-A3E1087DF4E2","layers":[{"animations":[],"layers":[],"texturedRectangle":{"singleTextureOpacity":1,"textXHeight":0,"shapePath":{"lineWidth":1,"flatness":0.59999999999999998,"lineCapStyle":0,"elements":[{"type":"MoveToPoint","points":[[146.65323312499822,31.542549924699983]]},{"type":"AddCurve","points":[[178.67983533667757,64.594760433496617],[178.67983533667757,118.18297241764469],[146.65323312499822,151.23518292644133]]},{"type":"AddCurve","points":[[114.62664206705449,184.28739343523796],[62.701273603084701,184.28739343523796],[30.674679756707064,151.23518292644133]]},{"type":"AddCurve","points":[[-1.3519147867789343,118.18297241764469],[-1.3519147867789343,64.594760433496617],[30.674679756707064,31.542549924699983]]},{"type":"AddCurve","points":[[62.701273603084701,-1.5096570985542712],[114.62664206705449,-1.5096570985542712],[146.65323312499822,31.542549924699983]]},{"type":"CloseSubpath"},{"type":"MoveToPoint","points":[[146.65323312499822,31.542549924699983]]}],"windingRule":0,"lineJoinStyle":0,"miterLimit":10},"isBackgroundTexture":true,"textBaseline":0,"isVerticalText":false,"textureType":5},"initialState":{"affineTransform":[1,0,0,1,0,0],"masksToBounds":false,"rotation":0,"scale":1,"position":{"pointX":86.845266150907491,"pointY":89.746605342740736},"width":177,"sublayerTransform":[1,0,0,0,0,1,0,0,0,0,1,0,0,0,0,1],"contentsRect":{"y":0,"x":0,"width":1,"height":1},"opacity":1,"edgeAntialiasingMask":0,"height":183,"hidden":true,"anchorPoint":{"pointX":0.5,"pointY":0.5}},"texture":"813CA334C8CDFC857C5488184BE80DF3"}]}]},{"animations":[],"initialState":{"affineTransform":[1,0,0,1,0,0],"masksToBounds":false,"rotation":0,"scale":1,"position":{"pointX":960,"pointY":540},"width":1920,"sublayerTransform":[1,0,0,0,0,1,0,0,0,0,1,0,0,0,0,1],"contentsRect":{"y":0,"x":0,"width":1,"height":1},"opacity":1,"edgeAntialiasingMask":251658240,"height":1080,"hidden":false,"anchorPoint":{"pointX":0.5,"pointY":0.5}},"layers":[{"animations":[],"initialState":{"affineTransform":[1,0,0,1,0,0],"masksToBounds":false,"rotation":0,"scale":1,"position":{"pointX":1515.6884846369328,"pointY":940.81912076009428},"width":198,"sublayerTransform":[1,0,0,0,0,1,0,0,0,0,1,0,0,0,0,1],"contentsRect":{"y":0,"x":0,"width":1,"height":1},"opacity":1,"edgeAntialiasingMask":251658240,"height":203,"hidden":false,"anchorPoint":{"pointX":0.5,"pointY":0.5}},"objectID":"91D4C10C-B13B-4F1A-A313-630B732A3675","layers":[{"animations":[],"layers":[],"texturedRectangle":{"singleTextureOpacity":1,"textXHeight":0,"shapePath":{"lineWidth":1,"flatness":0.59999999999999998,"lineCapStyle":0,"elements":[{"type":"MoveToPoint","points":[[164.14461810058515,34.199452052424817]]},{"type":"AddCurve","points":[[200.1648967343674,71.373231029050544],[200.1648967343674,131.64382465609719],[164.14461810058515,168.81760363272292]]},{"type":"AddCurve","points":[[128.1243520113951,205.99138260934865],[69.723956369302186,205.99138260934865],[33.703687143964089,168.81760363272292]]},{"type":"AddCurve","points":[[-2.3165828654109646,131.64382465609719],[-2.3165828654109646,71.373231029050544],[33.703687143964089,34.199452052424817]]},{"type":"AddCurve","points":[[69.723956369302186,-2.9743230040159006],[128.1243520113951,-2.9743230040159006],[164.14461810058515,34.199452052424817]]},{"type":"CloseSubpath"},{"type":"MoveToPoint","points":[[164.14461810058515,34.199452052424817]]}],"windingRule":0,"lineJoinStyle":0,"miterLimit":10},"isBackgroundTexture":true,"textBaseline":0,"isVerticalText":false,"textureType":5},"initialState":{"affineTransform":[1,0,0,1,0,0],"masksToBounds":false,"rotation":0,"scale":1,"position":{"pointX":97.311515363067201,"pointY":100.18087923990572},"width":198,"sublayerTransform":[1,0,0,0,0,1,0,0,0,0,1,0,0,0,0,1],"contentsRect":{"y":0,"x":0,"width":1,"height":1},"opacity":1,"edgeAntialiasingMask":0,"height":203,"hidden":true,"anchorPoint":{"pointX":0.5,"pointY":0.5}},"texture":"C4A3951E6F50F64E0D3B9F347CEB2AE1"}]}]}]}},{"effects":[{"beginTime":0,"baseLayer":{"animations":[],"initialState":{"affineTransform":[1,0,0,1,0,0],"masksToBounds":false,"rotation":0,"scale":1,"position":{"pointX":1400.090933499562,"pointY":391.45167809516045},"width":132,"sublayerTransform":[1,0,0,0,0,1,0,0,0,0,1,0,0,0,0,1],"contentsRect":{"y":0,"x":0,"width":1,"height":1},"opacity":1,"edgeAntialiasingMask":251658240,"height":137,"hidden":false,"anchorPoint":{"pointX":0.5,"pointY":0.5}},"objectID":"462E5D91-BC20-40AC-BB85-94174BDBC93B","layers":[{"animations":[],"initialState":{"affineTransform":[1,0,0,1,0,0],"masksToBounds":false,"rotation":0,"scale":1,"position":{"pointX":-374.09093349956197,"pointY":217.04832190483955},"width":132,"sublayerTransform":[1,0,0,0,0,1,0,0,0,0,1,-0.00035007912466775983,0,0,0,1],"contentsRect":{"y":0,"x":0,"width":1,"height":1},"opacity":1,"edgeAntialiasingMask":251658240,"height":137,"hidden":false,"anchorPoint":{"pointX":-2.8340222234815302,"pointY":1.5842943204732813}},"layers":[{"animations":[{"timeOffset":0,"from":{"scalar":true},"beginTime":1e-100,"repeatCount":0,"fillMode":"both","property":"hidden","autoreverses":false,"duration":0.01,"to":{"scalar":false}}],"layers":[],"texturedRectangle":{"singleTextureOpacity":1,"textXHeight":0,"shapePath":{"lineWidth":1,"flatness":0.59999999999999998,"lineCapStyle":0,"elements":[{"type":"MoveToPoint","points":[[108.219011892342,25.035222479737172]]},{"type":"AddCurve","points":[[131.58222905713978,49.146617535188966],[131.58222905713978,88.238906056140081],[108.219011892342,112.35030111159188]]},{"type":"AddCurve","points":[[84.855802864128464,136.46169616704367],[46.976553240093608,136.46169616704367],[23.613342177734012,112.35030111159188]]},{"type":"AddCurve","points":[[0.25013060683795629,88.238906056140081],[0.25013060683795629,49.146617535188966],[23.613342177734012,25.035222479737172]]},{"type":"AddCurve","points":[[46.976553240093608,0.92382996696824193],[84.855802864128464,0.92382996696824193],[108.219011892342,25.035222479737172]]},{"type":"CloseSubpath"},{"type":"MoveToPoint","points":[[108.219011892342,25.035222479737172]]}],"windingRule":0,"lineJoinStyle":0,"miterLimit":10},"isBackgroundTexture":true,"textBaseline":0,"isVerticalText":false,"textureType":5},"initialState":{"affineTransform":[1,0,0,1,0,0],"masksToBounds":false,"rotation":0,"scale":1,"position":{"pointX":64.90906650043803,"pointY":66.548321904839554},"width":132,"sublayerTransform":[1,0,0,0,0,1,0,0,0,0,1,0,0,0,0,1],"contentsRect":{"y":0,"x":0,"width":1,"height":1},"opacity":1,"edgeAntialiasingMask":0,"height":137,"hidden":true,"anchorPoint":{"pointX":0.5,"pointY":0.5}},"texture":"90133734F572A8BA02F77D41A855A5F8"}]}]},"effects":[],"duration":0.01,"type":"buildIn","attributes":{"direction":0},"name":"apple:appear","objectID":"462E5D91-BC20-40AC-BB85-94174BDBC93B"}],"automaticPlay":false,"hyperlinks":[],"accessibility":[{"text":"IMG_0013.jpeg","targetRectangle":{"y":-8.1713048771803187e-08,"x":166.87493884811059,"width":1586.2501220703125,"height":1080.0000000000002}}],"baseLayer":{"animations":[],"initialState":{"affineTransform":[1,0,0,1,0,0],"masksToBounds":false,"rotation":0,"scale":1,"position":{"pointX":960,"pointY":540},"width":1920,"sublayerTransform":[1,0,0,0,0,1,0,0,0,0,1,0,0,0,0,1],"contentsRect":{"y":0,"x":0,"width":1,"height":1},"opacity":1,"edgeAntialiasingMask":251658240,"height":1080,"hidden":false,"anchorPoint":{"pointX":0.5,"pointY":0.5}},"layers":[{"animations":[],"initialState":{"affineTransform":[1,0,0,1,0,0],"masksToBounds":false,"rotation":0,"scale":1,"position":{"pointX":960,"pointY":540},"width":1920,"sublayerTransform":[1,0,0,0,0,1,0,0,0,0,1,0,0,0,0,1],"contentsRect":{"y":0,"x":0,"width":1,"height":1},"opacity":1,"edgeAntialiasingMask":251658240,"height":1080,"hidden":false,"anchorPoint":{"pointX":0.5,"pointY":0.5}},"layers":[{"animations":[],"initialState":{"affineTransform":[1,0,0,1,0,0],"masksToBounds":false,"rotation":0,"scale":1,"position":{"pointX":960,"pointY":540},"width":1920,"sublayerTransform":[1,0,0,0,0,1,0,0,0,0,1,0,0,0,0,1],"contentsRect":{"y":0,"x":0,"width":1,"height":1},"opacity":1,"edgeAntialiasingMask":251658240,"height":1080,"hidden":false,"anchorPoint":{"pointX":0.5,"pointY":0.5}},"layers":[{"animations":[],"layers":[],"texturedRectangle":{"isBackgroundTexture":true,"singleTextureOpacity":1,"textureType":1,"textBaseline":0,"textXHeight":0,"isVerticalText":false},"initialState":{"affineTransform":[1,0,0,1,0,0],"masksToBounds":false,"rotation":0,"scale":1,"position":{"pointX":960,"pointY":540},"width":1920,"sublayerTransform":[1,0,0,0,0,1,0,0,0,0,1,0,0,0,0,1],"contentsRect":{"y":0,"x":0,"width":1,"height":1},"opacity":1,"edgeAntialiasingMask":0,"height":1080,"hidden":false,"anchorPoint":{"pointX":0.5,"pointY":0.5}},"texture":"C25C25FF361FB24FC35F6B120D2F252D"}]}]},{"animations":[],"initialState":{"affineTransform":[1,0,0,1,0,0],"masksToBounds":false,"rotation":0,"scale":1,"position":{"pointX":960,"pointY":540},"width":1920,"sublayerTransform":[1,0,0,0,0,1,0,0,0,0,1,0,0,0,0,1],"contentsRect":{"y":0,"x":0,"width":1,"height":1},"opacity":1,"edgeAntialiasingMask":251658240,"height":1080,"hidden":false,"anchorPoint":{"pointX":0.5,"pointY":0.5}},"layers":[{"animations":[],"initialState":{"affineTransform":[1,0,0,1,0,0],"masksToBounds":false,"rotation":0,"scale":1,"position":{"pointX":961.87493884811056,"pointY":541.4999999182869},"width":1590,"sublayerTransform":[1,0,0,0,0,1,0,0,0,0,1,0,0,0,0,1],"contentsRect":{"y":0,"x":0,"width":1,"height":1},"opacity":1,"edgeAntialiasingMask":251658240,"height":1083,"hidden":false,"anchorPoint":{"pointX":0.5,"pointY":0.5}},"layers":[{"animations":[],"layers":[],"texturedRectangle":{"isBackgroundTexture":true,"singleTextureOpacity":1,"textureType":5,"textBaseline":0,"textXHeight":0,"isVerticalText":false},"initialState":{"affineTransform":[1,0,0,1,0,0],"masksToBounds":false,"rotation":0,"scale":1,"position":{"pointX":793.12506115188944,"pointY":539.5000000817131},"width":1590,"sublayerTransform":[1,0,0,0,0,1,0,0,0,0,1,0,0,0,0,1],"contentsRect":{"y":0,"x":0,"width":1,"height":1},"opacity":1,"edgeAntialiasingMask":0,"height":1083,"hidden":false,"anchorPoint":{"pointX":0.5,"pointY":0.5}},"texture":"0CBCC992B49FB240DB36CA943C52B115"}]}]},{"animations":[],"initialState":{"affineTransform":[1,0,0,1,0,0],"masksToBounds":false,"rotation":0,"scale":1,"position":{"pointX":960,"pointY":540},"width":1920,"sublayerTransform":[1,0,0,0,0,1,0,0,0,0,1,0,0,0,0,1],"contentsRect":{"y":0,"x":0,"width":1,"height":1},"opacity":1,"edgeAntialiasingMask":251658240,"height":1080,"hidden":false,"anchorPoint":{"pointX":0.5,"pointY":0.5}},"layers":[{"animations":[],"initialState":{"affineTransform":[1,0,0,1,0,0],"masksToBounds":false,"rotation":0,"scale":1,"position":{"pointX":1672.7532986151359,"pointY":673.47668420808657},"width":237,"sublayerTransform":[1,0,0,0,0,1,0,0,0,0,1,0,0,0,0,1],"contentsRect":{"y":0,"x":0,"width":1,"height":1},"opacity":1,"edgeAntialiasingMask":251658240,"height":245,"hidden":false,"anchorPoint":{"pointX":0.5,"pointY":0.5}},"objectID":"F2A13A65-6739-4ECE-B5A7-FD53FE9543C8","layers":[{"animations":[],"layers":[],"texturedRectangle":{"singleTextureOpacity":1,"textXHeight":0,"shapePath":{"lineWidth":1,"flatness":0.59999999999999998,"lineCapStyle":0,"elements":[{"type":"MoveToPoint","points":[[197.77725933771535,40.889313213421588]]},{"type":"AddCurve","points":[[241.59101483260952,86.10615188720169],[241.59101483260952,159.41713230045571],[197.77725933771535,204.63397097423581]]},{"type":"AddCurve","points":[[153.96350384282096,249.85080964801591],[82.927370731200881,249.85080964801591],[39.113615236306714,204.63397097423581]]},{"type":"AddCurve","points":[[-4.7001402585876804,159.41713230045582],[-4.7001402585876804,86.10615188720169],[39.113615236306487,40.889313213421588]]},{"type":"AddCurve","points":[[82.927370731200881,-4.3275254603584017],[153.96350384282096,-4.3275254603585154],[197.77725933771535,40.889313213421588]]},{"type":"CloseSubpath"},{"type":"MoveToPoint","points":[[197.77725933771535,40.889313213421588]]}],"windingRule":0,"lineJoinStyle":0,"miterLimit":10},"isBackgroundTexture":true,"textBaseline":0,"isVerticalText":false,"textureType":5},"initialState":{"affineTransform":[1,0,0,1,0,0],"masksToBounds":false,"rotation":0,"scale":1,"position":{"pointX":117.24670138486408,"pointY":120.52331579191343},"width":237,"sublayerTransform":[1,0,0,0,0,1,0,0,0,0,1,0,0,0,0,1],"contentsRect":{"y":0,"x":0,"width":1,"height":1},"opacity":1,"edgeAntialiasingMask":0,"height":245,"hidden":false,"anchorPoint":{"pointX":0.5,"pointY":0.5}},"texture":"83408B2AE91F6BC206FBD4B66C03D0E1"}]}]},{"animations":[],"initialState":{"affineTransform":[1,0,0,1,0,0],"masksToBounds":false,"rotation":0,"scale":1,"position":{"pointX":960,"pointY":540},"width":1920,"sublayerTransform":[1,0,0,0,0,1,0,0,0,0,1,0,0,0,0,1],"contentsRect":{"y":0,"x":0,"width":1,"height":1},"opacity":1,"edgeAntialiasingMask":251658240,"height":1080,"hidden":false,"anchorPoint":{"pointX":0.5,"pointY":0.5}},"layers":[{"animations":[],"initialState":{"affineTransform":[1,0,0,1,0,0],"masksToBounds":false,"rotation":0,"scale":1,"position":{"pointX":1400.090933499562,"pointY":391.45167809516045},"width":132,"sublayerTransform":[1,0,0,0,0,1,0,0,0,0,1,0,0,0,0,1],"contentsRect":{"y":0,"x":0,"width":1,"height":1},"opacity":1,"edgeAntialiasingMask":251658240,"height":137,"hidden":false,"anchorPoint":{"pointX":0.5,"pointY":0.5}},"objectID":"462E5D91-BC20-40AC-BB85-94174BDBC93B","layers":[{"animations":[],"layers":[],"texturedRectangle":{"singleTextureOpacity":1,"textXHeight":0,"shapePath":{"lineWidth":1,"flatness":0.59999999999999998,"lineCapStyle":0,"elements":[{"type":"MoveToPoint","points":[[108.219011892342,25.035222479737172]]},{"type":"AddCurve","points":[[131.58222905713978,49.146617535188966],[131.58222905713978,88.238906056140081],[108.219011892342,112.35030111159188]]},{"type":"AddCurve","points":[[84.855802864128464,136.46169616704367],[46.976553240093608,136.46169616704367],[23.613342177734012,112.35030111159188]]},{"type":"AddCurve","points":[[0.25013060683795629,88.238906056140081],[0.25013060683795629,49.146617535188966],[23.613342177734012,25.035222479737172]]},{"type":"AddCurve","points":[[46.976553240093608,0.92382996696824193],[84.855802864128464,0.92382996696824193],[108.219011892342,25.035222479737172]]},{"type":"CloseSubpath"},{"type":"MoveToPoint","points":[[108.219011892342,25.035222479737172]]}],"windingRule":0,"lineJoinStyle":0,"miterLimit":10},"isBackgroundTexture":true,"textBaseline":0,"isVerticalText":false,"textureType":5},"initialState":{"affineTransform":[1,0,0,1,0,0],"masksToBounds":false,"rotation":0,"scale":1,"position":{"pointX":64.90906650043803,"pointY":66.548321904839554},"width":132,"sublayerTransform":[1,0,0,0,0,1,0,0,0,0,1,0,0,0,0,1],"contentsRect":{"y":0,"x":0,"width":1,"height":1},"opacity":1,"edgeAntialiasingMask":0,"height":137,"hidden":true,"anchorPoint":{"pointX":0.5,"pointY":0.5}},"texture":"90133734F572A8BA02F77D41A855A5F8"}]}]},{"animations":[],"initialState":{"affineTransform":[1,0,0,1,0,0],"masksToBounds":false,"rotation":0,"scale":1,"position":{"pointX":960,"pointY":540},"width":1920,"sublayerTransform":[1,0,0,0,0,1,0,0,0,0,1,0,0,0,0,1],"contentsRect":{"y":0,"x":0,"width":1,"height":1},"opacity":1,"edgeAntialiasingMask":251658240,"height":1080,"hidden":false,"anchorPoint":{"pointX":0.5,"pointY":0.5}},"layers":[{"animations":[],"initialState":{"affineTransform":[1,0,0,1,0,0],"masksToBounds":false,"rotation":0,"scale":1,"position":{"pointX":945.21406487519459,"pointY":964.83098255654579},"width":228,"sublayerTransform":[1,0,0,0,0,1,0,0,0,0,1,0,0,0,0,1],"contentsRect":{"y":0,"x":0,"width":1,"height":1},"opacity":1,"edgeAntialiasingMask":251658240,"height":235,"hidden":false,"anchorPoint":{"pointX":0.5,"pointY":0.5}},"objectID":"12A2E71C-DA99-46E0-943B-1E52D1E332BA","layers":[{"animations":[],"layers":[],"texturedRectangle":{"singleTextureOpacity":1,"textXHeight":0,"shapePath":{"lineWidth":1,"flatness":0.59999999999999998,"lineCapStyle":0,"elements":[{"type":"MoveToPoint","points":[[190.17563330299322,38.904559463333726]]},{"type":"AddCurve","points":[[232.25939852009446,82.335999919141841],[232.25939852009446,152.75226564222635],[190.17563330299322,196.18370609803446]]},{"type":"AddCurve","points":[[148.09188274218263,239.61514655384258],[79.860635455753936,239.61514655384258],[37.776881230870686,196.18370609803446]]},{"type":"AddCurve","points":[[-4.3068739100307312,152.75226564222635],[-4.3068739100307312,82.335999919141841],[37.776881230870686,38.904559463333726]]},{"type":"AddCurve","points":[[79.860635455753936,-4.5268764123835581],[148.09188274218263,-4.5268764123835581],[190.17563330299322,38.904559463333726]]},{"type":"CloseSubpath"},{"type":"MoveToPoint","points":[[190.17563330299322,38.904559463333726]]}],"windingRule":0,"lineJoinStyle":0,"miterLimit":10},"isBackgroundTexture":true,"textBaseline":0,"isVerticalText":false,"textureType":5},"initialState":{"affineTransform":[1,0,0,1,0,0],"masksToBounds":false,"rotation":0,"scale":1,"position":{"pointX":112.78593512480541,"pointY":116.16901744345421},"width":228,"sublayerTransform":[1,0,0,0,0,1,0,0,0,0,1,0,0,0,0,1],"contentsRect":{"y":0,"x":0,"width":1,"height":1},"opacity":1,"edgeAntialiasingMask":0,"height":235,"hidden":true,"anchorPoint":{"pointX":0.5,"pointY":0.5}},"texture":"8C9F0787747E2AC327B7ABBD70025D54"}]}]},{"animations":[],"initialState":{"affineTransform":[1,0,0,1,0,0],"masksToBounds":false,"rotation":0,"scale":1,"position":{"pointX":960,"pointY":540},"width":1920,"sublayerTransform":[1,0,0,0,0,1,0,0,0,0,1,0,0,0,0,1],"contentsRect":{"y":0,"x":0,"width":1,"height":1},"opacity":1,"edgeAntialiasingMask":251658240,"height":1080,"hidden":false,"anchorPoint":{"pointX":0.5,"pointY":0.5}},"layers":[{"animations":[],"initialState":{"affineTransform":[1,0,0,1,0,0],"masksToBounds":false,"rotation":0,"scale":1,"position":{"pointX":1197.1547338490925,"pointY":362.25339465725926},"width":177,"sublayerTransform":[1,0,0,0,0,1,0,0,0,0,1,0,0,0,0,1],"contentsRect":{"y":0,"x":0,"width":1,"height":1},"opacity":1,"edgeAntialiasingMask":251658240,"height":183,"hidden":false,"anchorPoint":{"pointX":0.5,"pointY":0.5}},"objectID":"15E40DE8-D105-4B85-B7C0-A3E1087DF4E2","layers":[{"animations":[],"layers":[],"texturedRectangle":{"singleTextureOpacity":1,"textXHeight":0,"shapePath":{"lineWidth":1,"flatness":0.59999999999999998,"lineCapStyle":0,"elements":[{"type":"MoveToPoint","points":[[146.65323312499822,31.542549924699983]]},{"type":"AddCurve","points":[[178.67983533667757,64.594760433496617],[178.67983533667757,118.18297241764469],[146.65323312499822,151.23518292644133]]},{"type":"AddCurve","points":[[114.62664206705449,184.28739343523796],[62.701273603084701,184.28739343523796],[30.674679756707064,151.23518292644133]]},{"type":"AddCurve","points":[[-1.3519147867789343,118.18297241764469],[-1.3519147867789343,64.594760433496617],[30.674679756707064,31.542549924699983]]},{"type":"AddCurve","points":[[62.701273603084701,-1.5096570985542712],[114.62664206705449,-1.5096570985542712],[146.65323312499822,31.542549924699983]]},{"type":"CloseSubpath"},{"type":"MoveToPoint","points":[[146.65323312499822,31.542549924699983]]}],"windingRule":0,"lineJoinStyle":0,"miterLimit":10},"isBackgroundTexture":true,"textBaseline":0,"isVerticalText":false,"textureType":5},"initialState":{"affineTransform":[1,0,0,1,0,0],"masksToBounds":false,"rotation":0,"scale":1,"position":{"pointX":86.845266150907491,"pointY":89.746605342740736},"width":177,"sublayerTransform":[1,0,0,0,0,1,0,0,0,0,1,0,0,0,0,1],"contentsRect":{"y":0,"x":0,"width":1,"height":1},"opacity":1,"edgeAntialiasingMask":0,"height":183,"hidden":false,"anchorPoint":{"pointX":0.5,"pointY":0.5}},"texture":"813CA334C8CDFC857C5488184BE80DF3"}]}]},{"animations":[],"initialState":{"affineTransform":[1,0,0,1,0,0],"masksToBounds":false,"rotation":0,"scale":1,"position":{"pointX":960,"pointY":540},"width":1920,"sublayerTransform":[1,0,0,0,0,1,0,0,0,0,1,0,0,0,0,1],"contentsRect":{"y":0,"x":0,"width":1,"height":1},"opacity":1,"edgeAntialiasingMask":251658240,"height":1080,"hidden":false,"anchorPoint":{"pointX":0.5,"pointY":0.5}},"layers":[{"animations":[],"initialState":{"affineTransform":[1,0,0,1,0,0],"masksToBounds":false,"rotation":0,"scale":1,"position":{"pointX":1515.6884846369328,"pointY":940.81912076009428},"width":198,"sublayerTransform":[1,0,0,0,0,1,0,0,0,0,1,0,0,0,0,1],"contentsRect":{"y":0,"x":0,"width":1,"height":1},"opacity":1,"edgeAntialiasingMask":251658240,"height":203,"hidden":false,"anchorPoint":{"pointX":0.5,"pointY":0.5}},"objectID":"91D4C10C-B13B-4F1A-A313-630B732A3675","layers":[{"animations":[],"layers":[],"texturedRectangle":{"singleTextureOpacity":1,"textXHeight":0,"shapePath":{"lineWidth":1,"flatness":0.59999999999999998,"lineCapStyle":0,"elements":[{"type":"MoveToPoint","points":[[164.14461810058515,34.199452052424817]]},{"type":"AddCurve","points":[[200.1648967343674,71.373231029050544],[200.1648967343674,131.64382465609719],[164.14461810058515,168.81760363272292]]},{"type":"AddCurve","points":[[128.1243520113951,205.99138260934865],[69.723956369302186,205.99138260934865],[33.703687143964089,168.81760363272292]]},{"type":"AddCurve","points":[[-2.3165828654109646,131.64382465609719],[-2.3165828654109646,71.373231029050544],[33.703687143964089,34.199452052424817]]},{"type":"AddCurve","points":[[69.723956369302186,-2.9743230040159006],[128.1243520113951,-2.9743230040159006],[164.14461810058515,34.199452052424817]]},{"type":"CloseSubpath"},{"type":"MoveToPoint","points":[[164.14461810058515,34.199452052424817]]}],"windingRule":0,"lineJoinStyle":0,"miterLimit":10},"isBackgroundTexture":true,"textBaseline":0,"isVerticalText":false,"textureType":5},"initialState":{"affineTransform":[1,0,0,1,0,0],"masksToBounds":false,"rotation":0,"scale":1,"position":{"pointX":97.311515363067201,"pointY":100.18087923990572},"width":198,"sublayerTransform":[1,0,0,0,0,1,0,0,0,0,1,0,0,0,0,1],"contentsRect":{"y":0,"x":0,"width":1,"height":1},"opacity":1,"edgeAntialiasingMask":0,"height":203,"hidden":true,"anchorPoint":{"pointX":0.5,"pointY":0.5}},"texture":"C4A3951E6F50F64E0D3B9F347CEB2AE1"}]}]}]}},{"effects":[{"beginTime":0,"baseLayer":{"animations":[],"initialState":{"affineTransform":[1,0,0,1,0,0],"masksToBounds":false,"rotation":0,"scale":1,"position":{"pointX":945.21406487519459,"pointY":964.83098255654579},"width":228,"sublayerTransform":[1,0,0,0,0,1,0,0,0,0,1,0,0,0,0,1],"contentsRect":{"y":0,"x":0,"width":1,"height":1},"opacity":1,"edgeAntialiasingMask":251658240,"height":235,"hidden":false,"anchorPoint":{"pointX":0.5,"pointY":0.5}},"objectID":"12A2E71C-DA99-46E0-943B-1E52D1E332BA","layers":[{"animations":[],"initialState":{"affineTransform":[1,0,0,1,0,0],"masksToBounds":false,"rotation":0,"scale":1,"position":{"pointX":128.78593512480541,"pointY":-307.33098255654579},"width":228,"sublayerTransform":[1,0,0,0,0,1,0,0,0,0,1,-0.00035007912466775983,0,0,0,1],"contentsRect":{"y":0,"x":0,"width":1,"height":1},"opacity":1,"edgeAntialiasingMask":251658240,"height":235,"hidden":false,"anchorPoint":{"pointX":0.56485059265265525,"pointY":-1.3077914151342374}},"layers":[{"animations":[{"timeOffset":0,"from":{"scalar":true},"beginTime":1e-100,"repeatCount":0,"fillMode":"both","property":"hidden","autoreverses":false,"duration":0.01,"to":{"scalar":false}}],"layers":[],"texturedRectangle":{"singleTextureOpacity":1,"textXHeight":0,"shapePath":{"lineWidth":1,"flatness":0.59999999999999998,"lineCapStyle":0,"elements":[{"type":"MoveToPoint","points":[[190.17563330299322,38.904559463333726]]},{"type":"AddCurve","points":[[232.25939852009446,82.335999919141841],[232.25939852009446,152.75226564222635],[190.17563330299322,196.18370609803446]]},{"type":"AddCurve","points":[[148.09188274218263,239.61514655384258],[79.860635455753936,239.61514655384258],[37.776881230870686,196.18370609803446]]},{"type":"AddCurve","points":[[-4.3068739100307312,152.75226564222635],[-4.3068739100307312,82.335999919141841],[37.776881230870686,38.904559463333726]]},{"type":"AddCurve","points":[[79.860635455753936,-4.5268764123835581],[148.09188274218263,-4.5268764123835581],[190.17563330299322,38.904559463333726]]},{"type":"CloseSubpath"},{"type":"MoveToPoint","points":[[190.17563330299322,38.904559463333726]]}],"windingRule":0,"lineJoinStyle":0,"miterLimit":10},"isBackgroundTexture":true,"textBaseline":0,"isVerticalText":false,"textureType":5},"initialState":{"affineTransform":[1,0,0,1,0,0],"masksToBounds":false,"rotation":0,"scale":1,"position":{"pointX":112.78593512480541,"pointY":116.16901744345421},"width":228,"sublayerTransform":[1,0,0,0,0,1,0,0,0,0,1,0,0,0,0,1],"contentsRect":{"y":0,"x":0,"width":1,"height":1},"opacity":1,"edgeAntialiasingMask":0,"height":235,"hidden":true,"anchorPoint":{"pointX":0.5,"pointY":0.5}},"texture":"8C9F0787747E2AC327B7ABBD70025D54"}]}]},"effects":[],"duration":0.01,"type":"buildIn","attributes":{"direction":0},"name":"apple:appear","objectID":"12A2E71C-DA99-46E0-943B-1E52D1E332BA"}],"automaticPlay":false,"hyperlinks":[],"accessibility":[{"text":"IMG_0013.jpeg","targetRectangle":{"y":-8.1713048771803187e-08,"x":166.87493884811059,"width":1586.2501220703125,"height":1080.0000000000002}}],"baseLayer":{"animations":[],"initialState":{"affineTransform":[1,0,0,1,0,0],"masksToBounds":false,"rotation":0,"scale":1,"position":{"pointX":960,"pointY":540},"width":1920,"sublayerTransform":[1,0,0,0,0,1,0,0,0,0,1,0,0,0,0,1],"contentsRect":{"y":0,"x":0,"width":1,"height":1},"opacity":1,"edgeAntialiasingMask":251658240,"height":1080,"hidden":false,"anchorPoint":{"pointX":0.5,"pointY":0.5}},"layers":[{"animations":[],"initialState":{"affineTransform":[1,0,0,1,0,0],"masksToBounds":false,"rotation":0,"scale":1,"position":{"pointX":960,"pointY":540},"width":1920,"sublayerTransform":[1,0,0,0,0,1,0,0,0,0,1,0,0,0,0,1],"contentsRect":{"y":0,"x":0,"width":1,"height":1},"opacity":1,"edgeAntialiasingMask":251658240,"height":1080,"hidden":false,"anchorPoint":{"pointX":0.5,"pointY":0.5}},"layers":[{"animations":[],"initialState":{"affineTransform":[1,0,0,1,0,0],"masksToBounds":false,"rotation":0,"scale":1,"position":{"pointX":960,"pointY":540},"width":1920,"sublayerTransform":[1,0,0,0,0,1,0,0,0,0,1,0,0,0,0,1],"contentsRect":{"y":0,"x":0,"width":1,"height":1},"opacity":1,"edgeAntialiasingMask":251658240,"height":1080,"hidden":false,"anchorPoint":{"pointX":0.5,"pointY":0.5}},"layers":[{"animations":[],"layers":[],"texturedRectangle":{"isBackgroundTexture":true,"singleTextureOpacity":1,"textureType":1,"textBaseline":0,"textXHeight":0,"isVerticalText":false},"initialState":{"affineTransform":[1,0,0,1,0,0],"masksToBounds":false,"rotation":0,"scale":1,"position":{"pointX":960,"pointY":540},"width":1920,"sublayerTransform":[1,0,0,0,0,1,0,0,0,0,1,0,0,0,0,1],"contentsRect":{"y":0,"x":0,"width":1,"height":1},"opacity":1,"edgeAntialiasingMask":0,"height":1080,"hidden":false,"anchorPoint":{"pointX":0.5,"pointY":0.5}},"texture":"C25C25FF361FB24FC35F6B120D2F252D"}]}]},{"animations":[],"initialState":{"affineTransform":[1,0,0,1,0,0],"masksToBounds":false,"rotation":0,"scale":1,"position":{"pointX":960,"pointY":540},"width":1920,"sublayerTransform":[1,0,0,0,0,1,0,0,0,0,1,0,0,0,0,1],"contentsRect":{"y":0,"x":0,"width":1,"height":1},"opacity":1,"edgeAntialiasingMask":251658240,"height":1080,"hidden":false,"anchorPoint":{"pointX":0.5,"pointY":0.5}},"layers":[{"animations":[],"initialState":{"affineTransform":[1,0,0,1,0,0],"masksToBounds":false,"rotation":0,"scale":1,"position":{"pointX":961.87493884811056,"pointY":541.4999999182869},"width":1590,"sublayerTransform":[1,0,0,0,0,1,0,0,0,0,1,0,0,0,0,1],"contentsRect":{"y":0,"x":0,"width":1,"height":1},"opacity":1,"edgeAntialiasingMask":251658240,"height":1083,"hidden":false,"anchorPoint":{"pointX":0.5,"pointY":0.5}},"layers":[{"animations":[],"layers":[],"texturedRectangle":{"isBackgroundTexture":true,"singleTextureOpacity":1,"textureType":5,"textBaseline":0,"textXHeight":0,"isVerticalText":false},"initialState":{"affineTransform":[1,0,0,1,0,0],"masksToBounds":false,"rotation":0,"scale":1,"position":{"pointX":793.12506115188944,"pointY":539.5000000817131},"width":1590,"sublayerTransform":[1,0,0,0,0,1,0,0,0,0,1,0,0,0,0,1],"contentsRect":{"y":0,"x":0,"width":1,"height":1},"opacity":1,"edgeAntialiasingMask":0,"height":1083,"hidden":false,"anchorPoint":{"pointX":0.5,"pointY":0.5}},"texture":"0CBCC992B49FB240DB36CA943C52B115"}]}]},{"animations":[],"initialState":{"affineTransform":[1,0,0,1,0,0],"masksToBounds":false,"rotation":0,"scale":1,"position":{"pointX":960,"pointY":540},"width":1920,"sublayerTransform":[1,0,0,0,0,1,0,0,0,0,1,0,0,0,0,1],"contentsRect":{"y":0,"x":0,"width":1,"height":1},"opacity":1,"edgeAntialiasingMask":251658240,"height":1080,"hidden":false,"anchorPoint":{"pointX":0.5,"pointY":0.5}},"layers":[{"animations":[],"initialState":{"affineTransform":[1,0,0,1,0,0],"masksToBounds":false,"rotation":0,"scale":1,"position":{"pointX":1672.7532986151359,"pointY":673.47668420808657},"width":237,"sublayerTransform":[1,0,0,0,0,1,0,0,0,0,1,0,0,0,0,1],"contentsRect":{"y":0,"x":0,"width":1,"height":1},"opacity":1,"edgeAntialiasingMask":251658240,"height":245,"hidden":false,"anchorPoint":{"pointX":0.5,"pointY":0.5}},"objectID":"F2A13A65-6739-4ECE-B5A7-FD53FE9543C8","layers":[{"animations":[],"layers":[],"texturedRectangle":{"singleTextureOpacity":1,"textXHeight":0,"shapePath":{"lineWidth":1,"flatness":0.59999999999999998,"lineCapStyle":0,"elements":[{"type":"MoveToPoint","points":[[197.77725933771535,40.889313213421588]]},{"type":"AddCurve","points":[[241.59101483260952,86.10615188720169],[241.59101483260952,159.41713230045571],[197.77725933771535,204.63397097423581]]},{"type":"AddCurve","points":[[153.96350384282096,249.85080964801591],[82.927370731200881,249.85080964801591],[39.113615236306714,204.63397097423581]]},{"type":"AddCurve","points":[[-4.7001402585876804,159.41713230045582],[-4.7001402585876804,86.10615188720169],[39.113615236306487,40.889313213421588]]},{"type":"AddCurve","points":[[82.927370731200881,-4.3275254603584017],[153.96350384282096,-4.3275254603585154],[197.77725933771535,40.889313213421588]]},{"type":"CloseSubpath"},{"type":"MoveToPoint","points":[[197.77725933771535,40.889313213421588]]}],"windingRule":0,"lineJoinStyle":0,"miterLimit":10},"isBackgroundTexture":true,"textBaseline":0,"isVerticalText":false,"textureType":5},"initialState":{"affineTransform":[1,0,0,1,0,0],"masksToBounds":false,"rotation":0,"scale":1,"position":{"pointX":117.24670138486408,"pointY":120.52331579191343},"width":237,"sublayerTransform":[1,0,0,0,0,1,0,0,0,0,1,0,0,0,0,1],"contentsRect":{"y":0,"x":0,"width":1,"height":1},"opacity":1,"edgeAntialiasingMask":0,"height":245,"hidden":false,"anchorPoint":{"pointX":0.5,"pointY":0.5}},"texture":"83408B2AE91F6BC206FBD4B66C03D0E1"}]}]},{"animations":[],"initialState":{"affineTransform":[1,0,0,1,0,0],"masksToBounds":false,"rotation":0,"scale":1,"position":{"pointX":960,"pointY":540},"width":1920,"sublayerTransform":[1,0,0,0,0,1,0,0,0,0,1,0,0,0,0,1],"contentsRect":{"y":0,"x":0,"width":1,"height":1},"opacity":1,"edgeAntialiasingMask":251658240,"height":1080,"hidden":false,"anchorPoint":{"pointX":0.5,"pointY":0.5}},"layers":[{"animations":[],"initialState":{"affineTransform":[1,0,0,1,0,0],"masksToBounds":false,"rotation":0,"scale":1,"position":{"pointX":1400.090933499562,"pointY":391.45167809516045},"width":132,"sublayerTransform":[1,0,0,0,0,1,0,0,0,0,1,0,0,0,0,1],"contentsRect":{"y":0,"x":0,"width":1,"height":1},"opacity":1,"edgeAntialiasingMask":251658240,"height":137,"hidden":false,"anchorPoint":{"pointX":0.5,"pointY":0.5}},"objectID":"462E5D91-BC20-40AC-BB85-94174BDBC93B","layers":[{"animations":[],"layers":[],"texturedRectangle":{"singleTextureOpacity":1,"textXHeight":0,"shapePath":{"lineWidth":1,"flatness":0.59999999999999998,"lineCapStyle":0,"elements":[{"type":"MoveToPoint","points":[[108.219011892342,25.035222479737172]]},{"type":"AddCurve","points":[[131.58222905713978,49.146617535188966],[131.58222905713978,88.238906056140081],[108.219011892342,112.35030111159188]]},{"type":"AddCurve","points":[[84.855802864128464,136.46169616704367],[46.976553240093608,136.46169616704367],[23.613342177734012,112.35030111159188]]},{"type":"AddCurve","points":[[0.25013060683795629,88.238906056140081],[0.25013060683795629,49.146617535188966],[23.613342177734012,25.035222479737172]]},{"type":"AddCurve","points":[[46.976553240093608,0.92382996696824193],[84.855802864128464,0.92382996696824193],[108.219011892342,25.035222479737172]]},{"type":"CloseSubpath"},{"type":"MoveToPoint","points":[[108.219011892342,25.035222479737172]]}],"windingRule":0,"lineJoinStyle":0,"miterLimit":10},"isBackgroundTexture":true,"textBaseline":0,"isVerticalText":false,"textureType":5},"initialState":{"affineTransform":[1,0,0,1,0,0],"masksToBounds":false,"rotation":0,"scale":1,"position":{"pointX":64.90906650043803,"pointY":66.548321904839554},"width":132,"sublayerTransform":[1,0,0,0,0,1,0,0,0,0,1,0,0,0,0,1],"contentsRect":{"y":0,"x":0,"width":1,"height":1},"opacity":1,"edgeAntialiasingMask":0,"height":137,"hidden":false,"anchorPoint":{"pointX":0.5,"pointY":0.5}},"texture":"90133734F572A8BA02F77D41A855A5F8"}]}]},{"animations":[],"initialState":{"affineTransform":[1,0,0,1,0,0],"masksToBounds":false,"rotation":0,"scale":1,"position":{"pointX":960,"pointY":540},"width":1920,"sublayerTransform":[1,0,0,0,0,1,0,0,0,0,1,0,0,0,0,1],"contentsRect":{"y":0,"x":0,"width":1,"height":1},"opacity":1,"edgeAntialiasingMask":251658240,"height":1080,"hidden":false,"anchorPoint":{"pointX":0.5,"pointY":0.5}},"layers":[{"animations":[],"initialState":{"affineTransform":[1,0,0,1,0,0],"masksToBounds":false,"rotation":0,"scale":1,"position":{"pointX":945.21406487519459,"pointY":964.83098255654579},"width":228,"sublayerTransform":[1,0,0,0,0,1,0,0,0,0,1,0,0,0,0,1],"contentsRect":{"y":0,"x":0,"width":1,"height":1},"opacity":1,"edgeAntialiasingMask":251658240,"height":235,"hidden":false,"anchorPoint":{"pointX":0.5,"pointY":0.5}},"objectID":"12A2E71C-DA99-46E0-943B-1E52D1E332BA","layers":[{"animations":[],"layers":[],"texturedRectangle":{"singleTextureOpacity":1,"textXHeight":0,"shapePath":{"lineWidth":1,"flatness":0.59999999999999998,"lineCapStyle":0,"elements":[{"type":"MoveToPoint","points":[[190.17563330299322,38.904559463333726]]},{"type":"AddCurve","points":[[232.25939852009446,82.335999919141841],[232.25939852009446,152.75226564222635],[190.17563330299322,196.18370609803446]]},{"type":"AddCurve","points":[[148.09188274218263,239.61514655384258],[79.860635455753936,239.61514655384258],[37.776881230870686,196.18370609803446]]},{"type":"AddCurve","points":[[-4.3068739100307312,152.75226564222635],[-4.3068739100307312,82.335999919141841],[37.776881230870686,38.904559463333726]]},{"type":"AddCurve","points":[[79.860635455753936,-4.5268764123835581],[148.09188274218263,-4.5268764123835581],[190.17563330299322,38.904559463333726]]},{"type":"CloseSubpath"},{"type":"MoveToPoint","points":[[190.17563330299322,38.904559463333726]]}],"windingRule":0,"lineJoinStyle":0,"miterLimit":10},"isBackgroundTexture":true,"textBaseline":0,"isVerticalText":false,"textureType":5},"initialState":{"affineTransform":[1,0,0,1,0,0],"masksToBounds":false,"rotation":0,"scale":1,"position":{"pointX":112.78593512480541,"pointY":116.16901744345421},"width":228,"sublayerTransform":[1,0,0,0,0,1,0,0,0,0,1,0,0,0,0,1],"contentsRect":{"y":0,"x":0,"width":1,"height":1},"opacity":1,"edgeAntialiasingMask":0,"height":235,"hidden":true,"anchorPoint":{"pointX":0.5,"pointY":0.5}},"texture":"8C9F0787747E2AC327B7ABBD70025D54"}]}]},{"animations":[],"initialState":{"affineTransform":[1,0,0,1,0,0],"masksToBounds":false,"rotation":0,"scale":1,"position":{"pointX":960,"pointY":540},"width":1920,"sublayerTransform":[1,0,0,0,0,1,0,0,0,0,1,0,0,0,0,1],"contentsRect":{"y":0,"x":0,"width":1,"height":1},"opacity":1,"edgeAntialiasingMask":251658240,"height":1080,"hidden":false,"anchorPoint":{"pointX":0.5,"pointY":0.5}},"layers":[{"animations":[],"initialState":{"affineTransform":[1,0,0,1,0,0],"masksToBounds":false,"rotation":0,"scale":1,"position":{"pointX":1197.1547338490925,"pointY":362.25339465725926},"width":177,"sublayerTransform":[1,0,0,0,0,1,0,0,0,0,1,0,0,0,0,1],"contentsRect":{"y":0,"x":0,"width":1,"height":1},"opacity":1,"edgeAntialiasingMask":251658240,"height":183,"hidden":false,"anchorPoint":{"pointX":0.5,"pointY":0.5}},"objectID":"15E40DE8-D105-4B85-B7C0-A3E1087DF4E2","layers":[{"animations":[],"layers":[],"texturedRectangle":{"singleTextureOpacity":1,"textXHeight":0,"shapePath":{"lineWidth":1,"flatness":0.59999999999999998,"lineCapStyle":0,"elements":[{"type":"MoveToPoint","points":[[146.65323312499822,31.542549924699983]]},{"type":"AddCurve","points":[[178.67983533667757,64.594760433496617],[178.67983533667757,118.18297241764469],[146.65323312499822,151.23518292644133]]},{"type":"AddCurve","points":[[114.62664206705449,184.28739343523796],[62.701273603084701,184.28739343523796],[30.674679756707064,151.23518292644133]]},{"type":"AddCurve","points":[[-1.3519147867789343,118.18297241764469],[-1.3519147867789343,64.594760433496617],[30.674679756707064,31.542549924699983]]},{"type":"AddCurve","points":[[62.701273603084701,-1.5096570985542712],[114.62664206705449,-1.5096570985542712],[146.65323312499822,31.542549924699983]]},{"type":"CloseSubpath"},{"type":"MoveToPoint","points":[[146.65323312499822,31.542549924699983]]}],"windingRule":0,"lineJoinStyle":0,"miterLimit":10},"isBackgroundTexture":true,"textBaseline":0,"isVerticalText":false,"textureType":5},"initialState":{"affineTransform":[1,0,0,1,0,0],"masksToBounds":false,"rotation":0,"scale":1,"position":{"pointX":86.845266150907491,"pointY":89.746605342740736},"width":177,"sublayerTransform":[1,0,0,0,0,1,0,0,0,0,1,0,0,0,0,1],"contentsRect":{"y":0,"x":0,"width":1,"height":1},"opacity":1,"edgeAntialiasingMask":0,"height":183,"hidden":false,"anchorPoint":{"pointX":0.5,"pointY":0.5}},"texture":"813CA334C8CDFC857C5488184BE80DF3"}]}]},{"animations":[],"initialState":{"affineTransform":[1,0,0,1,0,0],"masksToBounds":false,"rotation":0,"scale":1,"position":{"pointX":960,"pointY":540},"width":1920,"sublayerTransform":[1,0,0,0,0,1,0,0,0,0,1,0,0,0,0,1],"contentsRect":{"y":0,"x":0,"width":1,"height":1},"opacity":1,"edgeAntialiasingMask":251658240,"height":1080,"hidden":false,"anchorPoint":{"pointX":0.5,"pointY":0.5}},"layers":[{"animations":[],"initialState":{"affineTransform":[1,0,0,1,0,0],"masksToBounds":false,"rotation":0,"scale":1,"position":{"pointX":1515.6884846369328,"pointY":940.81912076009428},"width":198,"sublayerTransform":[1,0,0,0,0,1,0,0,0,0,1,0,0,0,0,1],"contentsRect":{"y":0,"x":0,"width":1,"height":1},"opacity":1,"edgeAntialiasingMask":251658240,"height":203,"hidden":false,"anchorPoint":{"pointX":0.5,"pointY":0.5}},"objectID":"91D4C10C-B13B-4F1A-A313-630B732A3675","layers":[{"animations":[],"layers":[],"texturedRectangle":{"singleTextureOpacity":1,"textXHeight":0,"shapePath":{"lineWidth":1,"flatness":0.59999999999999998,"lineCapStyle":0,"elements":[{"type":"MoveToPoint","points":[[164.14461810058515,34.199452052424817]]},{"type":"AddCurve","points":[[200.1648967343674,71.373231029050544],[200.1648967343674,131.64382465609719],[164.14461810058515,168.81760363272292]]},{"type":"AddCurve","points":[[128.1243520113951,205.99138260934865],[69.723956369302186,205.99138260934865],[33.703687143964089,168.81760363272292]]},{"type":"AddCurve","points":[[-2.3165828654109646,131.64382465609719],[-2.3165828654109646,71.373231029050544],[33.703687143964089,34.199452052424817]]},{"type":"AddCurve","points":[[69.723956369302186,-2.9743230040159006],[128.1243520113951,-2.9743230040159006],[164.14461810058515,34.199452052424817]]},{"type":"CloseSubpath"},{"type":"MoveToPoint","points":[[164.14461810058515,34.199452052424817]]}],"windingRule":0,"lineJoinStyle":0,"miterLimit":10},"isBackgroundTexture":true,"textBaseline":0,"isVerticalText":false,"textureType":5},"initialState":{"affineTransform":[1,0,0,1,0,0],"masksToBounds":false,"rotation":0,"scale":1,"position":{"pointX":97.311515363067201,"pointY":100.18087923990572},"width":198,"sublayerTransform":[1,0,0,0,0,1,0,0,0,0,1,0,0,0,0,1],"contentsRect":{"y":0,"x":0,"width":1,"height":1},"opacity":1,"edgeAntialiasingMask":0,"height":203,"hidden":true,"anchorPoint":{"pointX":0.5,"pointY":0.5}},"texture":"C4A3951E6F50F64E0D3B9F347CEB2AE1"}]}]}]}},{"effects":[{"beginTime":0,"baseLayer":{"animations":[],"initialState":{"affineTransform":[1,0,0,1,0,0],"masksToBounds":false,"rotation":0,"scale":1,"position":{"pointX":1515.6884846369328,"pointY":940.81912076009428},"width":198,"sublayerTransform":[1,0,0,0,0,1,0,0,0,0,1,0,0,0,0,1],"contentsRect":{"y":0,"x":0,"width":1,"height":1},"opacity":1,"edgeAntialiasingMask":251658240,"height":203,"hidden":false,"anchorPoint":{"pointX":0.5,"pointY":0.5}},"objectID":"91D4C10C-B13B-4F1A-A313-630B732A3675","layers":[{"animations":[],"initialState":{"affineTransform":[1,0,0,1,0,0],"masksToBounds":false,"rotation":0,"scale":1,"position":{"pointX":-456.6884846369328,"pointY":-299.31912076009428},"width":198,"sublayerTransform":[1,0,0,0,0,1,0,0,0,0,1,-0.00035007912466775983,0,0,0,1],"contentsRect":{"y":0,"x":0,"width":1,"height":1},"opacity":1,"edgeAntialiasingMask":251658240,"height":203,"hidden":false,"anchorPoint":{"pointX":-2.3065074981663272,"pointY":-1.474478427389627}},"layers":[{"animations":[{"timeOffset":0,"from":{"scalar":true},"beginTime":1e-100,"repeatCount":0,"fillMode":"both","property":"hidden","autoreverses":false,"duration":0.01,"to":{"scalar":false}}],"layers":[],"texturedRectangle":{"singleTextureOpacity":1,"textXHeight":0,"shapePath":{"lineWidth":1,"flatness":0.59999999999999998,"lineCapStyle":0,"elements":[{"type":"MoveToPoint","points":[[164.14461810058515,34.199452052424817]]},{"type":"AddCurve","points":[[200.1648967343674,71.373231029050544],[200.1648967343674,131.64382465609719],[164.14461810058515,168.81760363272292]]},{"type":"AddCurve","points":[[128.1243520113951,205.99138260934865],[69.723956369302186,205.99138260934865],[33.703687143964089,168.81760363272292]]},{"type":"AddCurve","points":[[-2.3165828654109646,131.64382465609719],[-2.3165828654109646,71.373231029050544],[33.703687143964089,34.199452052424817]]},{"type":"AddCurve","points":[[69.723956369302186,-2.9743230040159006],[128.1243520113951,-2.9743230040159006],[164.14461810058515,34.199452052424817]]},{"type":"CloseSubpath"},{"type":"MoveToPoint","points":[[164.14461810058515,34.199452052424817]]}],"windingRule":0,"lineJoinStyle":0,"miterLimit":10},"isBackgroundTexture":true,"textBaseline":0,"isVerticalText":false,"textureType":5},"initialState":{"affineTransform":[1,0,0,1,0,0],"masksToBounds":false,"rotation":0,"scale":1,"position":{"pointX":97.311515363067201,"pointY":100.18087923990572},"width":198,"sublayerTransform":[1,0,0,0,0,1,0,0,0,0,1,0,0,0,0,1],"contentsRect":{"y":0,"x":0,"width":1,"height":1},"opacity":1,"edgeAntialiasingMask":0,"height":203,"hidden":true,"anchorPoint":{"pointX":0.5,"pointY":0.5}},"texture":"C4A3951E6F50F64E0D3B9F347CEB2AE1"}]}]},"effects":[],"duration":0.01,"type":"buildIn","attributes":{"direction":0},"name":"apple:appear","objectID":"91D4C10C-B13B-4F1A-A313-630B732A3675"}],"automaticPlay":false,"hyperlinks":[],"accessibility":[{"text":"IMG_0013.jpeg","targetRectangle":{"y":-8.1713048771803187e-08,"x":166.87493884811059,"width":1586.2501220703125,"height":1080.0000000000002}}],"baseLayer":{"animations":[],"initialState":{"affineTransform":[1,0,0,1,0,0],"masksToBounds":false,"rotation":0,"scale":1,"position":{"pointX":960,"pointY":540},"width":1920,"sublayerTransform":[1,0,0,0,0,1,0,0,0,0,1,0,0,0,0,1],"contentsRect":{"y":0,"x":0,"width":1,"height":1},"opacity":1,"edgeAntialiasingMask":251658240,"height":1080,"hidden":false,"anchorPoint":{"pointX":0.5,"pointY":0.5}},"layers":[{"animations":[],"initialState":{"affineTransform":[1,0,0,1,0,0],"masksToBounds":false,"rotation":0,"scale":1,"position":{"pointX":960,"pointY":540},"width":1920,"sublayerTransform":[1,0,0,0,0,1,0,0,0,0,1,0,0,0,0,1],"contentsRect":{"y":0,"x":0,"width":1,"height":1},"opacity":1,"edgeAntialiasingMask":251658240,"height":1080,"hidden":false,"anchorPoint":{"pointX":0.5,"pointY":0.5}},"layers":[{"animations":[],"initialState":{"affineTransform":[1,0,0,1,0,0],"masksToBounds":false,"rotation":0,"scale":1,"position":{"pointX":960,"pointY":540},"width":1920,"sublayerTransform":[1,0,0,0,0,1,0,0,0,0,1,0,0,0,0,1],"contentsRect":{"y":0,"x":0,"width":1,"height":1},"opacity":1,"edgeAntialiasingMask":251658240,"height":1080,"hidden":false,"anchorPoint":{"pointX":0.5,"pointY":0.5}},"layers":[{"animations":[],"layers":[],"texturedRectangle":{"isBackgroundTexture":true,"singleTextureOpacity":1,"textureType":1,"textBaseline":0,"textXHeight":0,"isVerticalText":false},"initialState":{"affineTransform":[1,0,0,1,0,0],"masksToBounds":false,"rotation":0,"scale":1,"position":{"pointX":960,"pointY":540},"width":1920,"sublayerTransform":[1,0,0,0,0,1,0,0,0,0,1,0,0,0,0,1],"contentsRect":{"y":0,"x":0,"width":1,"height":1},"opacity":1,"edgeAntialiasingMask":0,"height":1080,"hidden":false,"anchorPoint":{"pointX":0.5,"pointY":0.5}},"texture":"C25C25FF361FB24FC35F6B120D2F252D"}]}]},{"animations":[],"initialState":{"affineTransform":[1,0,0,1,0,0],"masksToBounds":false,"rotation":0,"scale":1,"position":{"pointX":960,"pointY":540},"width":1920,"sublayerTransform":[1,0,0,0,0,1,0,0,0,0,1,0,0,0,0,1],"contentsRect":{"y":0,"x":0,"width":1,"height":1},"opacity":1,"edgeAntialiasingMask":251658240,"height":1080,"hidden":false,"anchorPoint":{"pointX":0.5,"pointY":0.5}},"layers":[{"animations":[],"initialState":{"affineTransform":[1,0,0,1,0,0],"masksToBounds":false,"rotation":0,"scale":1,"position":{"pointX":961.87493884811056,"pointY":541.4999999182869},"width":1590,"sublayerTransform":[1,0,0,0,0,1,0,0,0,0,1,0,0,0,0,1],"contentsRect":{"y":0,"x":0,"width":1,"height":1},"opacity":1,"edgeAntialiasingMask":251658240,"height":1083,"hidden":false,"anchorPoint":{"pointX":0.5,"pointY":0.5}},"layers":[{"animations":[],"layers":[],"texturedRectangle":{"isBackgroundTexture":true,"singleTextureOpacity":1,"textureType":5,"textBaseline":0,"textXHeight":0,"isVerticalText":false},"initialState":{"affineTransform":[1,0,0,1,0,0],"masksToBounds":false,"rotation":0,"scale":1,"position":{"pointX":793.12506115188944,"pointY":539.5000000817131},"width":1590,"sublayerTransform":[1,0,0,0,0,1,0,0,0,0,1,0,0,0,0,1],"contentsRect":{"y":0,"x":0,"width":1,"height":1},"opacity":1,"edgeAntialiasingMask":0,"height":1083,"hidden":false,"anchorPoint":{"pointX":0.5,"pointY":0.5}},"texture":"0CBCC992B49FB240DB36CA943C52B115"}]}]},{"animations":[],"initialState":{"affineTransform":[1,0,0,1,0,0],"masksToBounds":false,"rotation":0,"scale":1,"position":{"pointX":960,"pointY":540},"width":1920,"sublayerTransform":[1,0,0,0,0,1,0,0,0,0,1,0,0,0,0,1],"contentsRect":{"y":0,"x":0,"width":1,"height":1},"opacity":1,"edgeAntialiasingMask":251658240,"height":1080,"hidden":false,"anchorPoint":{"pointX":0.5,"pointY":0.5}},"layers":[{"animations":[],"initialState":{"affineTransform":[1,0,0,1,0,0],"masksToBounds":false,"rotation":0,"scale":1,"position":{"pointX":1672.7532986151359,"pointY":673.47668420808657},"width":237,"sublayerTransform":[1,0,0,0,0,1,0,0,0,0,1,0,0,0,0,1],"contentsRect":{"y":0,"x":0,"width":1,"height":1},"opacity":1,"edgeAntialiasingMask":251658240,"height":245,"hidden":false,"anchorPoint":{"pointX":0.5,"pointY":0.5}},"objectID":"F2A13A65-6739-4ECE-B5A7-FD53FE9543C8","layers":[{"animations":[],"layers":[],"texturedRectangle":{"singleTextureOpacity":1,"textXHeight":0,"shapePath":{"lineWidth":1,"flatness":0.59999999999999998,"lineCapStyle":0,"elements":[{"type":"MoveToPoint","points":[[197.77725933771535,40.889313213421588]]},{"type":"AddCurve","points":[[241.59101483260952,86.10615188720169],[241.59101483260952,159.41713230045571],[197.77725933771535,204.63397097423581]]},{"type":"AddCurve","points":[[153.96350384282096,249.85080964801591],[82.927370731200881,249.85080964801591],[39.113615236306714,204.63397097423581]]},{"type":"AddCurve","points":[[-4.7001402585876804,159.41713230045582],[-4.7001402585876804,86.10615188720169],[39.113615236306487,40.889313213421588]]},{"type":"AddCurve","points":[[82.927370731200881,-4.3275254603584017],[153.96350384282096,-4.3275254603585154],[197.77725933771535,40.889313213421588]]},{"type":"CloseSubpath"},{"type":"MoveToPoint","points":[[197.77725933771535,40.889313213421588]]}],"windingRule":0,"lineJoinStyle":0,"miterLimit":10},"isBackgroundTexture":true,"textBaseline":0,"isVerticalText":false,"textureType":5},"initialState":{"affineTransform":[1,0,0,1,0,0],"masksToBounds":false,"rotation":0,"scale":1,"position":{"pointX":117.24670138486408,"pointY":120.52331579191343},"width":237,"sublayerTransform":[1,0,0,0,0,1,0,0,0,0,1,0,0,0,0,1],"contentsRect":{"y":0,"x":0,"width":1,"height":1},"opacity":1,"edgeAntialiasingMask":0,"height":245,"hidden":false,"anchorPoint":{"pointX":0.5,"pointY":0.5}},"texture":"83408B2AE91F6BC206FBD4B66C03D0E1"}]}]},{"animations":[],"initialState":{"affineTransform":[1,0,0,1,0,0],"masksToBounds":false,"rotation":0,"scale":1,"position":{"pointX":960,"pointY":540},"width":1920,"sublayerTransform":[1,0,0,0,0,1,0,0,0,0,1,0,0,0,0,1],"contentsRect":{"y":0,"x":0,"width":1,"height":1},"opacity":1,"edgeAntialiasingMask":251658240,"height":1080,"hidden":false,"anchorPoint":{"pointX":0.5,"pointY":0.5}},"layers":[{"animations":[],"initialState":{"affineTransform":[1,0,0,1,0,0],"masksToBounds":false,"rotation":0,"scale":1,"position":{"pointX":1400.090933499562,"pointY":391.45167809516045},"width":132,"sublayerTransform":[1,0,0,0,0,1,0,0,0,0,1,0,0,0,0,1],"contentsRect":{"y":0,"x":0,"width":1,"height":1},"opacity":1,"edgeAntialiasingMask":251658240,"height":137,"hidden":false,"anchorPoint":{"pointX":0.5,"pointY":0.5}},"objectID":"462E5D91-BC20-40AC-BB85-94174BDBC93B","layers":[{"animations":[],"layers":[],"texturedRectangle":{"singleTextureOpacity":1,"textXHeight":0,"shapePath":{"lineWidth":1,"flatness":0.59999999999999998,"lineCapStyle":0,"elements":[{"type":"MoveToPoint","points":[[108.219011892342,25.035222479737172]]},{"type":"AddCurve","points":[[131.58222905713978,49.146617535188966],[131.58222905713978,88.238906056140081],[108.219011892342,112.35030111159188]]},{"type":"AddCurve","points":[[84.855802864128464,136.46169616704367],[46.976553240093608,136.46169616704367],[23.613342177734012,112.35030111159188]]},{"type":"AddCurve","points":[[0.25013060683795629,88.238906056140081],[0.25013060683795629,49.146617535188966],[23.613342177734012,25.035222479737172]]},{"type":"AddCurve","points":[[46.976553240093608,0.92382996696824193],[84.855802864128464,0.92382996696824193],[108.219011892342,25.035222479737172]]},{"type":"CloseSubpath"},{"type":"MoveToPoint","points":[[108.219011892342,25.035222479737172]]}],"windingRule":0,"lineJoinStyle":0,"miterLimit":10},"isBackgroundTexture":true,"textBaseline":0,"isVerticalText":false,"textureType":5},"initialState":{"affineTransform":[1,0,0,1,0,0],"masksToBounds":false,"rotation":0,"scale":1,"position":{"pointX":64.90906650043803,"pointY":66.548321904839554},"width":132,"sublayerTransform":[1,0,0,0,0,1,0,0,0,0,1,0,0,0,0,1],"contentsRect":{"y":0,"x":0,"width":1,"height":1},"opacity":1,"edgeAntialiasingMask":0,"height":137,"hidden":false,"anchorPoint":{"pointX":0.5,"pointY":0.5}},"texture":"90133734F572A8BA02F77D41A855A5F8"}]}]},{"animations":[],"initialState":{"affineTransform":[1,0,0,1,0,0],"masksToBounds":false,"rotation":0,"scale":1,"position":{"pointX":960,"pointY":540},"width":1920,"sublayerTransform":[1,0,0,0,0,1,0,0,0,0,1,0,0,0,0,1],"contentsRect":{"y":0,"x":0,"width":1,"height":1},"opacity":1,"edgeAntialiasingMask":251658240,"height":1080,"hidden":false,"anchorPoint":{"pointX":0.5,"pointY":0.5}},"layers":[{"animations":[],"initialState":{"affineTransform":[1,0,0,1,0,0],"masksToBounds":false,"rotation":0,"scale":1,"position":{"pointX":945.21406487519459,"pointY":964.83098255654579},"width":228,"sublayerTransform":[1,0,0,0,0,1,0,0,0,0,1,0,0,0,0,1],"contentsRect":{"y":0,"x":0,"width":1,"height":1},"opacity":1,"edgeAntialiasingMask":251658240,"height":235,"hidden":false,"anchorPoint":{"pointX":0.5,"pointY":0.5}},"objectID":"12A2E71C-DA99-46E0-943B-1E52D1E332BA","layers":[{"animations":[],"layers":[],"texturedRectangle":{"singleTextureOpacity":1,"textXHeight":0,"shapePath":{"lineWidth":1,"flatness":0.59999999999999998,"lineCapStyle":0,"elements":[{"type":"MoveToPoint","points":[[190.17563330299322,38.904559463333726]]},{"type":"AddCurve","points":[[232.25939852009446,82.335999919141841],[232.25939852009446,152.75226564222635],[190.17563330299322,196.18370609803446]]},{"type":"AddCurve","points":[[148.09188274218263,239.61514655384258],[79.860635455753936,239.61514655384258],[37.776881230870686,196.18370609803446]]},{"type":"AddCurve","points":[[-4.3068739100307312,152.75226564222635],[-4.3068739100307312,82.335999919141841],[37.776881230870686,38.904559463333726]]},{"type":"AddCurve","points":[[79.860635455753936,-4.5268764123835581],[148.09188274218263,-4.5268764123835581],[190.17563330299322,38.904559463333726]]},{"type":"CloseSubpath"},{"type":"MoveToPoint","points":[[190.17563330299322,38.904559463333726]]}],"windingRule":0,"lineJoinStyle":0,"miterLimit":10},"isBackgroundTexture":true,"textBaseline":0,"isVerticalText":false,"textureType":5},"initialState":{"affineTransform":[1,0,0,1,0,0],"masksToBounds":false,"rotation":0,"scale":1,"position":{"pointX":112.78593512480541,"pointY":116.16901744345421},"width":228,"sublayerTransform":[1,0,0,0,0,1,0,0,0,0,1,0,0,0,0,1],"contentsRect":{"y":0,"x":0,"width":1,"height":1},"opacity":1,"edgeAntialiasingMask":0,"height":235,"hidden":false,"anchorPoint":{"pointX":0.5,"pointY":0.5}},"texture":"8C9F0787747E2AC327B7ABBD70025D54"}]}]},{"animations":[],"initialState":{"affineTransform":[1,0,0,1,0,0],"masksToBounds":false,"rotation":0,"scale":1,"position":{"pointX":960,"pointY":540},"width":1920,"sublayerTransform":[1,0,0,0,0,1,0,0,0,0,1,0,0,0,0,1],"contentsRect":{"y":0,"x":0,"width":1,"height":1},"opacity":1,"edgeAntialiasingMask":251658240,"height":1080,"hidden":false,"anchorPoint":{"pointX":0.5,"pointY":0.5}},"layers":[{"animations":[],"initialState":{"affineTransform":[1,0,0,1,0,0],"masksToBounds":false,"rotation":0,"scale":1,"position":{"pointX":1197.1547338490925,"pointY":362.25339465725926},"width":177,"sublayerTransform":[1,0,0,0,0,1,0,0,0,0,1,0,0,0,0,1],"contentsRect":{"y":0,"x":0,"width":1,"height":1},"opacity":1,"edgeAntialiasingMask":251658240,"height":183,"hidden":false,"anchorPoint":{"pointX":0.5,"pointY":0.5}},"objectID":"15E40DE8-D105-4B85-B7C0-A3E1087DF4E2","layers":[{"animations":[],"layers":[],"texturedRectangle":{"singleTextureOpacity":1,"textXHeight":0,"shapePath":{"lineWidth":1,"flatness":0.59999999999999998,"lineCapStyle":0,"elements":[{"type":"MoveToPoint","points":[[146.65323312499822,31.542549924699983]]},{"type":"AddCurve","points":[[178.67983533667757,64.594760433496617],[178.67983533667757,118.18297241764469],[146.65323312499822,151.23518292644133]]},{"type":"AddCurve","points":[[114.62664206705449,184.28739343523796],[62.701273603084701,184.28739343523796],[30.674679756707064,151.23518292644133]]},{"type":"AddCurve","points":[[-1.3519147867789343,118.18297241764469],[-1.3519147867789343,64.594760433496617],[30.674679756707064,31.542549924699983]]},{"type":"AddCurve","points":[[62.701273603084701,-1.5096570985542712],[114.62664206705449,-1.5096570985542712],[146.65323312499822,31.542549924699983]]},{"type":"CloseSubpath"},{"type":"MoveToPoint","points":[[146.65323312499822,31.542549924699983]]}],"windingRule":0,"lineJoinStyle":0,"miterLimit":10},"isBackgroundTexture":true,"textBaseline":0,"isVerticalText":false,"textureType":5},"initialState":{"affineTransform":[1,0,0,1,0,0],"masksToBounds":false,"rotation":0,"scale":1,"position":{"pointX":86.845266150907491,"pointY":89.746605342740736},"width":177,"sublayerTransform":[1,0,0,0,0,1,0,0,0,0,1,0,0,0,0,1],"contentsRect":{"y":0,"x":0,"width":1,"height":1},"opacity":1,"edgeAntialiasingMask":0,"height":183,"hidden":false,"anchorPoint":{"pointX":0.5,"pointY":0.5}},"texture":"813CA334C8CDFC857C5488184BE80DF3"}]}]},{"animations":[],"initialState":{"affineTransform":[1,0,0,1,0,0],"masksToBounds":false,"rotation":0,"scale":1,"position":{"pointX":960,"pointY":540},"width":1920,"sublayerTransform":[1,0,0,0,0,1,0,0,0,0,1,0,0,0,0,1],"contentsRect":{"y":0,"x":0,"width":1,"height":1},"opacity":1,"edgeAntialiasingMask":251658240,"height":1080,"hidden":false,"anchorPoint":{"pointX":0.5,"pointY":0.5}},"layers":[{"animations":[],"initialState":{"affineTransform":[1,0,0,1,0,0],"masksToBounds":false,"rotation":0,"scale":1,"position":{"pointX":1515.6884846369328,"pointY":940.81912076009428},"width":198,"sublayerTransform":[1,0,0,0,0,1,0,0,0,0,1,0,0,0,0,1],"contentsRect":{"y":0,"x":0,"width":1,"height":1},"opacity":1,"edgeAntialiasingMask":251658240,"height":203,"hidden":false,"anchorPoint":{"pointX":0.5,"pointY":0.5}},"objectID":"91D4C10C-B13B-4F1A-A313-630B732A3675","layers":[{"animations":[],"layers":[],"texturedRectangle":{"singleTextureOpacity":1,"textXHeight":0,"shapePath":{"lineWidth":1,"flatness":0.59999999999999998,"lineCapStyle":0,"elements":[{"type":"MoveToPoint","points":[[164.14461810058515,34.199452052424817]]},{"type":"AddCurve","points":[[200.1648967343674,71.373231029050544],[200.1648967343674,131.64382465609719],[164.14461810058515,168.81760363272292]]},{"type":"AddCurve","points":[[128.1243520113951,205.99138260934865],[69.723956369302186,205.99138260934865],[33.703687143964089,168.81760363272292]]},{"type":"AddCurve","points":[[-2.3165828654109646,131.64382465609719],[-2.3165828654109646,71.373231029050544],[33.703687143964089,34.199452052424817]]},{"type":"AddCurve","points":[[69.723956369302186,-2.9743230040159006],[128.1243520113951,-2.9743230040159006],[164.14461810058515,34.199452052424817]]},{"type":"CloseSubpath"},{"type":"MoveToPoint","points":[[164.14461810058515,34.199452052424817]]}],"windingRule":0,"lineJoinStyle":0,"miterLimit":10},"isBackgroundTexture":true,"textBaseline":0,"isVerticalText":false,"textureType":5},"initialState":{"affineTransform":[1,0,0,1,0,0],"masksToBounds":false,"rotation":0,"scale":1,"position":{"pointX":97.311515363067201,"pointY":100.18087923990572},"width":198,"sublayerTransform":[1,0,0,0,0,1,0,0,0,0,1,0,0,0,0,1],"contentsRect":{"y":0,"x":0,"width":1,"height":1},"opacity":1,"edgeAntialiasingMask":0,"height":203,"hidden":true,"anchorPoint":{"pointX":0.5,"pointY":0.5}},"texture":"C4A3951E6F50F64E0D3B9F347CEB2AE1"}]}]}]}},{"effects":[{"beginTime":0,"baseLayer":{"animations":[],"initialState":{"affineTransform":[1,0,0,1,0,0],"masksToBounds":false,"rotation":0,"scale":1,"position":{"pointX":960,"pointY":540},"width":1920,"sublayerTransform":[1,0,0,0,0,1,0,0,0,0,1,0,0,0,0,1],"contentsRect":{"y":0,"x":0,"width":1,"height":1},"opacity":1,"edgeAntialiasingMask":251658240,"height":1080,"hidden":false,"anchorPoint":{"pointX":0.5,"pointY":0.5}},"objectID":"0","layers":[{"animations":[],"initialState":{"affineTransform":[1,0,0,1,0,0],"masksToBounds":false,"rotation":0,"scale":1,"position":{"pointX":960,"pointY":540},"width":1920,"sublayerTransform":[1,0,0,0,0,1,0,0,0,0,1,-0.00035007912466775983,0,0,0,1],"contentsRect":{"y":0,"x":0,"width":1,"height":1},"opacity":1,"edgeAntialiasingMask":251658240,"height":1080,"hidden":false,"anchorPoint":{"pointX":0.5,"pointY":0.5}},"layers":[{"animations":[],"layers":[],"texturedRectangle":{"isBackgroundTexture":false,"singleTextureOpacity":1,"textureType":0,"textBaseline":0,"textXHeight":0,"isVerticalText":false},"initialState":{"affineTransform":[1,0,0,1,0,0],"masksToBounds":false,"rotation":0,"scale":1,"position":{"pointX":960,"pointY":540},"width":1920,"sublayerTransform":[1,0,0,0,0,1,0,0,0,0,1,0,0,0,0,1],"contentsRect":{"y":0,"x":0,"width":1,"height":1},"opacity":1,"edgeAntialiasingMask":0,"height":1080,"hidden":false,"anchorPoint":{"pointX":0.5,"pointY":0.5}},"texture":"15F29FF383634C416491853B012D32A9"},{"animations":[{"timeOffset":0,"from":{"scalar":false},"beginTime":0,"repeatCount":0,"fillMode":"both","property":"hidden","autoreverses":false,"duration":0.01,"to":{"scalar":true}}],"layers":[],"texturedRectangle":{"isBackgroundTexture":false,"singleTextureOpacity":1,"textureType":0,"textBaseline":0,"textXHeight":0,"isVerticalText":false},"initialState":{"affineTransform":[1,0,0,1,0,0],"masksToBounds":false,"rotation":0,"scale":1,"position":{"pointX":960,"pointY":540},"width":1920,"sublayerTransform":[1,0,0,0,0,1,0,0,0,0,1,0,0,0,0,1],"contentsRect":{"y":0,"x":0,"width":1,"height":1},"opacity":1,"edgeAntialiasingMask":0,"height":1080,"hidden":false,"anchorPoint":{"pointX":0.5,"pointY":0.5}},"texture":"FEF403319AD5AC6FABBB18660ADA8AE2"}]}]},"effects":[],"duration":0.01,"type":"transition","attributes":{"direction":0},"name":"none","objectID":"0"}],"automaticPlay":false,"hyperlinks":[],"accessibility":[{"text":"IMG_0013.jpeg","targetRectangle":{"y":-8.1713048771803187e-08,"x":166.87493884811059,"width":1586.2501220703125,"height":1080.0000000000002}}],"baseLayer":{"animations":[],"initialState":{"affineTransform":[1,0,0,1,0,0],"masksToBounds":false,"rotation":0,"scale":1,"position":{"pointX":960,"pointY":540},"width":1920,"sublayerTransform":[1,0,0,0,0,1,0,0,0,0,1,0,0,0,0,1],"contentsRect":{"y":0,"x":0,"width":1,"height":1},"opacity":1,"edgeAntialiasingMask":251658240,"height":1080,"hidden":false,"anchorPoint":{"pointX":0.5,"pointY":0.5}},"objectID":"0","layers":[{"animations":[],"initialState":{"affineTransform":[1,0,0,1,0,0],"masksToBounds":false,"rotation":0,"scale":1,"position":{"pointX":960,"pointY":540},"width":1920,"sublayerTransform":[1,0,0,0,0,1,0,0,0,0,1,-0.00035007912466775983,0,0,0,1],"contentsRect":{"y":0,"x":0,"width":1,"height":1},"opacity":1,"edgeAntialiasingMask":251658240,"height":1080,"hidden":false,"anchorPoint":{"pointX":0.5,"pointY":0.5}},"layers":[{"animations":[],"layers":[],"texturedRectangle":{"isBackgroundTexture":false,"singleTextureOpacity":1,"textureType":0,"textBaseline":0,"textXHeight":0,"isVerticalText":false},"initialState":{"affineTransform":[1,0,0,1,0,0],"masksToBounds":false,"rotation":0,"scale":1,"position":{"pointX":960,"pointY":540},"width":1920,"sublayerTransform":[1,0,0,0,0,1,0,0,0,0,1,0,0,0,0,1],"contentsRect":{"y":0,"x":0,"width":1,"height":1},"opacity":1,"edgeAntialiasingMask":0,"height":1080,"hidden":false,"anchorPoint":{"pointX":0.5,"pointY":0.5}},"texture":"FEF403319AD5AC6FABBB18660ADA8AE2"}]}]}}]}